{
  "scores": [
    {
      "year": "2024",
      "month": "October",
      "day": "15",
      "file": "2024/October/15.tsv",
      "date": "2024-10-15",
      "performance_90_day": -10.596468152538296,
      "performance_annualized": -36.52816427941216,
      "total_stocks": 23
    },
    {
      "year": "2024",
      "month": "November",
      "day": "2",
      "file": "2024/November/2.tsv",
      "date": "2024-11-02",
      "performance_90_day": 0.47843554050118575,
      "performance_annualized": 1.9559028582294191,
      "total_stocks": 23
    },
    {
      "year": "2024",
      "month": "November",
      "day": "15",
      "file": "2024/November/15.tsv",
      "date": "2024-11-15",
      "performance_90_day": 6.070877750937328,
      "performance_annualized": 27.021653057772465,
      "total_stocks": 20
    },
    {
      "year": "2024",
      "month": "December",
      "day": "3",
      "file": "2024/December/3.tsv",
      "date": "2024-12-3",
      "performance_90_day": -12.97702160840258,
      "performance_annualized": -43.11281823170415,
      "total_stocks": 21
    },
    {
      "year": "2024",
      "month": "December",
      "day": "15",
      "file": "2024/December/15.tsv",
      "date": "2024-12-15",
      "performance_90_day": -6.5151151890413646,
      "performance_annualized": -24.15539972665488,
      "total_stocks": 20
    },
    {
      "year": "2024",
      "month": "December",
      "day": "29",
      "file": "2024/December/29.tsv",
      "date": "2024-12-29",
      "performance_90_day": 3.937749930489853,
      "performance_annualized": 17.175424906804192,
      "total_stocks": 23
    },
    {
      "year": "2025",
      "month": "January",
      "day": "6",
      "file": "2025/January/6.tsv",
      "date": "2025-01-06",
      "performance_90_day": -4.675630515830862,
      "performance_annualized": -18.024411969926433,
      "total_stocks": 21
    },
    {
      "year": "2025",
      "month": "January",
      "day": "15",
      "file": "2025/January/15.tsv",
      "date": "2025-01-15",
      "performance_90_day": -6.352873298042878,
      "performance_annualized": -23.38478866006396,
      "total_stocks": 20
    },
    {
      "year": "2025",
      "month": "February",
      "day": "5",
      "file": "2025/February/5.tsv",
      "date": "2025-02-05",
      "performance_90_day": 0.19559942408913636,
      "performance_annualized": 0.7955581694911729,
      "total_stocks": 23
    },
    {
      "year": "2025",
      "month": "February",
      "day": "15",
      "file": "2025/February/15.tsv",
      "date": "2025-02-15",
      "performance_90_day": 1.5599463207634314,
      "performance_annualized": 6.483420750536428,
      "total_stocks": 20
    },
    {
      "year": "2025",
      "month": "February",
      "day": "28",
      "file": "2025/February/28.tsv",
      "date": "2025-02-28",
      "performance_90_day": 0.5508766243813251,
      "performance_annualized": 2.254544892295063,
      "total_stocks": 23
    },
    {
      "year": "2025",
      "month": "March",
      "day": "5",
      "file": "2025/March/5.tsv",
      "date": "2025-03-05",
      "performance_90_day": -0.07045030355041249,
      "performance_annualized": -0.2856029516447811,
      "total_stocks": 20
    },
    {
      "year": "2025",
      "month": "March",
      "day": "12",
      "file": "2025/March/12.tsv",
      "date": "2025-03-12",
      "performance_90_day": 5.413003216398942,
      "performance_annualized": 23.854628344013463,
      "total_stocks": 22
    },
    {
      "year": "2025",
      "month": "March",
      "day": "21",
      "file": "2025/March/21.tsv",
      "date": "2025-03-21",
      "performance_90_day": 5.672681768671852,
      "performance_annualized": 25.412673143857667,
      "total_stocks": 21
    },
    {
      "year": "2025",
      "month": "April",
      "day": "4",
      "file": "2025/April/4.tsv",
      "date": "2025-04-04",
      "performance_90_day": 17.682088734710387,
      "performance_annualized": 93.62714581099452,
      "total_stocks": 20
    },
    {
      "year": "2025",
      "month": "April",
      "day": "15",
      "file": "2025/April/15.tsv",
      "date": "2025-04-15",
      "performance_90_day": 23.771358198646556,
      "performance_annualized": 137.620261331392,
      "total_stocks": 20
    },
    {
      "year": "2025",
      "month": "April",
      "day": "20",
      "file": "2025/April/20.tsv",
      "date": "2025-04-20",
      "performance_90_day": 27.898266829482147,
      "performance_annualized": 174.51454326382665,
      "total_stocks": 22
    },
    {
      "year": "2025",
      "month": "April",
      "day": "22",
      "file": "2025/April/22.tsv",
      "date": "2025-04-22",
      "performance_90_day": 23.636815765705272,
      "performance_annualized": 136.57373938336391,
      "total_stocks": 20
    },
    {
      "year": "2025",
      "month": "May",
      "day": "1",
      "file": "2025/May/1.tsv",
      "date": "2025-05-01",
      "performance_90_day": 18.473271002983616,
      "performance_annualized": 98.9647036844706,
      "total_stocks": 20
    },
    {
      "year": "2025",
      "month": "May",
      "day": "15",
      "file": "2025/May/15.tsv",
      "date": "2025-05-15",
      "performance_90_day": 9.919094996748376,
      "performance_annualized": 46.787309246687194,
      "total_stocks": 20
    },
    {
      "year": "2025",
      "month": "May",
      "day": "27",
      "file": "2025/May/27.tsv",
      "date": "2025-05-27",
      "performance_90_day": 1.845116191129466,
      "performance_annualized": 7.702060168080283,
      "total_stocks": 22
    },
    {
      "year": "2025",
      "month": "June",
      "day": "5",
      "file": "2025/June/05.tsv",
      "date": "2025-06-05",
      "performance_90_day": 11.038832930327588,
      "performance_annualized": 52.950977128004006,
      "total_stocks": 24
    },
    {
      "year": "2025",
      "month": "June",
      "day": "11",
      "file": "2025/June/11.tsv",
      "date": "2025-06-11",
      "performance_90_day": 9.20883395826232,
      "performance_annualized": 42.9758817655878,
      "total_stocks": 25
    },
    {
      "year": "2025",
      "month": "June",
      "day": "20",
      "file": "2025/June/20.tsv",
      "date": "2025-06-20",
      "performance_90_day": 20.74876778498709,
      "performance_annualized": 114.93508898536513,
      "total_stocks": 19
    },
    {
      "year": "2025",
      "month": "June",
      "day": "21",
      "file": "2025/June/21.tsv",
      "date": "2025-06-21",
      "performance_90_day": 17.200709144412816,
      "performance_annualized": 90.4328594014339,
      "total_stocks": 19
    },
    {
      "year": "2025",
      "month": "June",
      "day": "22",
      "file": "2025/June/22.tsv",
      "date": "2025-06-22",
      "performance_90_day": 8.99849225168226,
      "performance_annualized": 42.420061926496835,
      "total_stocks": 19
    },
    {
      "year": "2025",
      "month": "June",
      "day": "23",
      "file": "2025/June/23.tsv",
      "date": "2025-06-23",
      "performance_90_day": 7.893132627477145,
      "performance_annualized": 37.07019423310596,
      "total_stocks": 19
    },
    {
      "year": "2025",
      "month": "June",
      "day": "24",
      "file": "2025/June/24.tsv",
      "date": "2025-06-24",
      "performance_90_day": 6.978156756605454,
      "performance_annualized": 31.488970246243888,
      "total_stocks": 19
    },
    {
      "year": "2025",
      "month": "June",
      "day": "25",
      "file": "2025/June/25.tsv",
      "date": "2025-06-25",
      "performance_90_day": 14.378712047340889,
      "performance_annualized": 72.4980848495276,
      "total_stocks": 20
    },
    {
      "year": "2025",
      "month": "June",
      "day": "26",
      "file": "2025/June/26.tsv",
      "date": "2025-06-26",
      "performance_90_day": 15.754195666229233,
      "performance_annualized": 81.07282454174063,
      "total_stocks": 20
    },
    {
      "year": "2025",
      "month": "June",
      "day": "27",
      "file": "2025/June/27.tsv",
      "date": "2025-06-27",
      "performance_90_day": 7.692977067621463,
      "performance_annualized": 35.09122144543069,
      "total_stocks": 20
    },
    {
      "year": "2025",
      "month": "June",
      "day": "28",
      "file": "2025/June/28.tsv",
      "date": "2025-06-28",
      "performance_90_day": 10.21515266417215,
      "performance_annualized": 48.398428673194374,
      "total_stocks": 20
    },
    {
      "year": "2025",
      "month": "June",
      "day": "29",
      "file": "2025/June/29.tsv",
      "date": "2025-06-29",
      "performance_90_day": 15.282390824346551,
      "performance_annualized": 79.25491986828894,
      "total_stocks": 20
    },
    {
      "year": "2025",
      "month": "June",
      "day": "30",
      "file": "2025/June/30.tsv",
      "date": "2025-06-30",
      "performance_90_day": 15.282390824346557,
      "performance_annualized": 80.44773597810615,
      "total_stocks": 20
    },
    {
      "year": "2025",
      "month": "July",
      "day": "01",
      "file": "2025/July/01.tsv",
      "date": "2025-07-01",
      "performance_90_day": 14.36918018276639,
      "performance_annualized": 72.43975252143152,
      "total_stocks": 20
    },
    {
      "year": "2025",
      "month": "July",
      "day": "02",
      "file": "2025/July/02.tsv",
      "date": "2025-07-02",
      "performance_90_day": 26.46256168367903,
      "performance_annualized": 159.29591878719594,
      "total_stocks": 20
    },
    {
      "year": "2025",
      "month": "July",
      "day": "03",
      "file": "2025/July/03.tsv",
      "date": "2025-07-03",
      "performance_90_day": 27.449411060385927,
      "performance_annualized": 167.6061184232209,
      "total_stocks": 20
    },
    {
      "year": "2025",
      "month": "July",
      "day": "04",
      "file": "2025/July/04.tsv",
      "date": "2025-07-04",
      "performance_90_day": 28.124346453950288,
      "performance_annualized": 173.4041901294999,
      "total_stocks": 20
    },
    {
      "year": "2025",
      "month": "July",
      "day": "05",
      "file": "2025/July/05.tsv",
      "date": "2025-07-05",
      "performance_90_day": 25.482740355902852,
      "performance_annualized": 153.85286380830664,
      "total_stocks": 20
    },
    {
      "year": "2025",
      "month": "July",
      "day": "06",
      "file": "2025/July/06.tsv",
      "date": "2025-07-06",
      "performance_90_day": 1148.1011767430375,
      "performance_annualized": 3548520.1047221003,
      "total_stocks": 20
    },
    {
      "year": "2025",
      "month": "July",
      "day": "07",
      "file": "2025/July/07.tsv",
      "date": "2025-07-07",
      "performance_90_day": 1148.22861537151,
      "performance_annualized": 4004371.4570336095,
      "total_stocks": 20
    },
    {
      "year": "2025",
      "month": "July",
      "day": "10",
      "file": "2025/July/10.tsv",
      "date": "2025-07-10",
      "performance_90_day": 1019.5686803112256,
      "performance_annualized": 3643220.8318958366,
      "total_stocks": 20
    },
    {
      "year": "2025",
      "month": "July",
      "day": "11",
      "file": "2025/July/11.tsv",
      "date": "2025-07-11",
      "performance_90_day": 1132.908450458047,
      "performance_annualized": 6320420.381121061,
      "total_stocks": 20
    },
    {
      "year": "2025",
      "month": "July",
      "day": "12",
      "file": "2025/July/12.tsv",
      "date": "2025-07-12",
      "performance_90_day": 1183.1500980516305,
      "performance_annualized": 8640922.90117558,
      "total_stocks": 20
    },
    {
      "year": "2025",
      "month": "July",
      "day": "13",
      "file": "2025/July/13.tsv",
      "date": "2025-07-13",
      "performance_90_day": 1167.8234954779823,
      "performance_annualized": 9418320.775354834,
      "total_stocks": 20
    },
    {
      "year": "2025",
      "month": "July",
      "day": "14",
      "file": "2025/July/14.tsv",
      "date": "2025-07-14",
      "performance_90_day": 509.8582364298524,
      "performance_annualized": 384545.50988025306,
      "total_stocks": 20
    },
    {
      "year": "2025",
      "month": "July",
      "day": "15",
      "file": "2025/July/15.tsv",
      "date": "2025-07-15",
      "performance_90_day": 469.3696279047572,
      "performance_annualized": 310716.0078928201,
      "total_stocks": 20
    },
    {
      "year": "2025",
      "month": "July",
      "day": "16",
      "file": "2025/July/16.tsv",
      "date": "2025-07-16",
      "performance_90_day": 471.71243662461745,
      "performance_annualized": 351160.9800723339,
      "total_stocks": 20
    },
    {
      "year": "2025",
      "month": "July",
      "day": "17",
      "file": "2025/July/17.tsv",
      "date": "2025-07-17",
      "performance_90_day": 513.7548321040222,
      "performance_annualized": 546738.4460797012,
      "total_stocks": 20
    },
    {
      "year": "2025",
      "month": "July",
      "day": "18",
      "file": "2025/July/18.tsv",
      "date": "2025-07-18",
      "performance_90_day": 5.881721806344254,
      "performance_annualized": 31.609652513927443,
      "total_stocks": 20
    },
    {
      "year": "2025",
      "month": "July",
      "day": "19",
      "file": "2025/July/19.tsv",
      "date": "2025-07-19",
      "performance_90_day": 13.90274071097269,
      "performance_annualized": 88.50437232280134,
      "total_stocks": 20
    },
    {
      "year": "2025",
      "month": "July",
      "day": "20",
      "file": "2025/July/20.tsv",
      "date": "2025-07-20",
      "performance_90_day": 21.986230995452622,
      "performance_annualized": 166.69436806687284,
      "total_stocks": 20
    },
    {
      "year": "2025",
      "month": "July",
      "day": "21",
      "file": "2025/July/21.tsv",
      "date": "2025-07-21",
      "performance_90_day": 21.986230995452622,
      "performance_annualized": 170.30224368332708,
      "total_stocks": 20
    },
    {
      "year": "2025",
      "month": "July",
      "day": "22",
      "file": "2025/July/22.tsv",
      "date": "2025-07-22",
      "performance_90_day": 19.00090030496713,
      "performance_annualized": 141.69079349822476,
      "total_stocks": 20
    },
    {
      "year": "2025",
      "month": "July",
      "day": "23",
      "file": "2025/July/23.tsv",
      "date": "2025-07-23",
      "performance_90_day": 20.88791012372365,
      "performance_annualized": 165.34300917718178,
      "total_stocks": 20
    },
    {
      "year": "2025",
      "month": "July",
      "day": "24",
      "file": "2025/July/24.tsv",
      "date": "2025-07-24",
      "performance_90_day": 20.659048509328947,
      "performance_annualized": 166.4206522372101,
      "total_stocks": 20
    },
    {
      "year": "2025",
      "month": "July",
      "day": "25",
      "file": "2025/July/25.tsv",
      "date": "2025-07-25",
      "performance_90_day": 123.64553671556696,
      "performance_annualized": 6985.810065806931,
      "total_stocks": 20
    },
    {
      "year": "2025",
      "month": "July",
      "day": "26",
      "file": "2025/July/26.tsv",
      "date": "2025-07-26",
      "performance_90_day": 16.06136800247982,
      "performance_annualized": 122.5658283949748,
      "total_stocks": 20
    },
    {
      "year": "2025",
      "month": "July",
      "day": "27",
      "file": "2025/July/27.tsv",
      "date": "2025-07-27",
      "performance_90_day": 15.739710817314656,
      "performance_annualized": 121.85733469371348,
      "total_stocks": 20
    },
    {
      "year": "2025",
      "month": "July",
      "day": "28",
      "file": "2025/July/28.tsv",
      "date": "2025-07-28",
      "performance_90_day": 26.31387442878083,
      "performance_annualized": 264.28338990102026,
      "total_stocks": 20
    },
    {
      "year": "2025",
      "month": "July",
      "day": "29",
      "file": "2025/July/29.tsv",
      "date": "2025-07-29",
      "performance_90_day": 28.85060900127429,
      "performance_annualized": 315.5289730561516,
      "total_stocks": 20
    },
    {
      "year": "2025",
      "month": "July",
      "day": "30",
      "file": "2025/July/30.tsv",
      "date": "2025-07-30",
      "performance_90_day": 7.566868518700585,
      "performance_annualized": 51.63181584583339,
      "total_stocks": 20
    },
    {
      "year": "2025",
      "month": "July",
      "day": "31",
      "file": "2025/July/31.tsv",
      "date": "2025-07-31",
      "performance_90_day": 60.92861235285534,
      "performance_annualized": 1477.5421128319183,
      "total_stocks": 20
    },
    {
      "year": "2025",
      "month": "August",
      "day": "01",
      "file": "2025/August/01.tsv",
      "date": "2025-08-01",
      "performance_90_day": 25.80555833336873,
      "performance_annualized": 286.6736341192542,
      "total_stocks": 20
    },
    {
      "year": "2025",
      "month": "August",
      "day": "02",
      "file": "2025/August/02.tsv",
      "date": "2025-08-02",
      "performance_90_day": 23.545010373018552,
      "performance_annualized": 254.66820965867427,
      "total_stocks": 20
    },
    {
      "year": "2025",
      "month": "August",
      "day": "03",
      "file": "2025/August/03.tsv",
      "date": "2025-08-03",
      "performance_90_day": 20.109901996306093,
      "performance_annualized": 205.0956543250138,
      "total_stocks": 20
    },
    {
      "year": "2025",
      "month": "August",
      "day": "08",
      "file": "2025/August/08.tsv",
      "date": "2025-08-08",
      "performance_90_day": 12.882703259438236,
      "performance_annualized": 123.61132070501228,
      "total_stocks": 20
    },
    {
      "year": "2025",
      "month": "August",
      "day": "09",
      "file": "2025/August/09.tsv",
      "date": "2025-08-09",
      "performance_90_day": 11.136557505179445,
      "performance_annualized": 104.25431897723465,
      "total_stocks": 20
    },
    {
      "year": "2025",
      "month": "August",
      "day": "10",
      "file": "2025/August/10.tsv",
      "date": "2025-08-10"
    },
    {
      "year": "2025",
      "month": "August",
      "day": "11",
      "file": "2025/August/11.tsv",
      "date": "2025-08-11"
    },
    {
      "year": "2025",
      "month": "August",
      "day": "12",
      "file": "2025/August/12.tsv",
      "date": "2025-08-12"
    },
    {
      "year": "2025",
      "month": "August",
      "day": "13",
      "file": "2025/August/13.tsv",
      "date": "2025-08-13"
    },
    {
      "year": "2025",
      "month": "August",
      "day": "14",
      "file": "2025/August/14.tsv",
      "date": "2025-08-14"
    },
    {
      "year": "2025",
      "month": "August",
      "day": "15",
      "file": "2025/August/15.tsv",
      "date": "2025-08-15"
    },
    {
      "year": "2025",
      "month": "August",
      "day": "16",
      "file": "2025/August/16.tsv",
      "date": "2025-08-16"
    },
    {
      "year": "2025",
      "month": "August",
      "day": "17",
      "file": "2025/August/17.tsv",
      "date": "2025-08-17"
    },
    {
      "year": "2025",
      "month": "August",
      "day": "18",
      "file": "2025/August/18.tsv",
      "date": "2025-08-18"
    },
    {
      "year": "2025",
      "month": "August",
      "day": "19",
      "file": "2025/August/19.tsv",
      "date": "2025-08-19"
    },
    {
      "year": "2025",
      "month": "August",
      "day": "20",
      "file": "2025/August/20.tsv",
      "date": "2025-08-20",
      "performance_90_day": 13.06086849173477,
      "performance_annualized": 183.69046626582613,
      "total_stocks": 20
    },
    {
      "year": "2025",
      "month": "August",
      "day": "21",
      "file": "2025/August/21.tsv",
      "date": "2025-08-21",
      "performance_90_day": 11.591871559157292,
      "performance_annualized": 159.55725220625706,
      "total_stocks": 20
    },
    {
      "year": "2025",
      "month": "August",
      "day": "22",
      "file": "2025/August/22.tsv",
      "date": "2025-08-22",
      "performance_90_day": 10.373120291678868,
      "performance_annualized": 140.9070213821816,
      "total_stocks": 20
    },
    {
      "year": "2025",
      "month": "August",
      "day": "23",
      "file": "2025/August/23.tsv",
      "date": "2025-08-23",
      "performance_90_day": 6.407473145526592,
      "performance_annualized": 76.31500075081603,
      "total_stocks": 20
    },
    {
      "year": "2025",
      "month": "August",
      "day": "24",
      "file": "2025/August/24.tsv",
      "date": "2025-08-24",
      "performance_90_day": 10.500083289268057,
      "performance_annualized": 154.74606085043652,
      "total_stocks": 20
    },
    {
      "year": "2025",
      "month": "August",
      "day": "25",
      "file": "2025/August/25.tsv",
      "date": "2025-08-25",
      "performance_90_day": 8.885309165599981,
      "performance_annualized": 126.64334152899586,
      "total_stocks": 20
    },
    {
      "year": "2025",
      "month": "August",
      "day": "26",
      "file": "2025/August/26.tsv",
      "date": "2025-08-26",
      "performance_90_day": 5.796042970564947,
      "performance_annualized": 74.40257718562466,
      "total_stocks": 20
    },
    {
      "year": "2025",
      "month": "August",
      "day": "27",
      "file": "2025/August/27.tsv",
      "date": "2025-08-27",
      "performance_90_day": 4.165268153998258,
      "performance_annualized": 51.29130078487818,
      "total_stocks": 20
    },
    {
      "year": "2025",
      "month": "August",
      "day": "29",
      "file": "2025/August/29.tsv",
      "date": "2025-08-29",
      "performance_90_day": 2.5177311048768676,
      "performance_annualized": 30.6200045117659,
      "total_stocks": 20
    },
    {
      "year": "2025",
      "month": "August",
      "day": "30",
      "file": "2025/August/30.tsv",
      "date": "2025-08-30",
      "performance_90_day": 2.981177520684633,
      "performance_annualized": 38.422357294394025,
      "total_stocks": 20
    },
    {
      "year": "2025",
      "month": "August",
      "day": "31",
      "file": "2025/August/31.tsv",
      "date": "2025-08-31",
      "performance_90_day": 1.3333507074779083,
      "performance_annualized": 16.321043994886498,
      "total_stocks": 20
    },
    {
      "year": "2025",
      "month": "September",
      "day": "01",
      "file": "2025/September/01.tsv",
      "date": "2025-09-01",
      "performance_90_day": 3.610355235394187,
      "performance_annualized": 51.87421217653658,
      "total_stocks": 20
    },
    {
      "year": "2025",
      "month": "September",
      "day": "02",
      "file": "2025/September/02.tsv",
      "date": "2025-09-02",
      "performance_90_day": 3.610355235394187,
      "performance_annualized": 54.00453367971772,
      "total_stocks": 20
    },
    {
      "year": "2025",
      "month": "September",
      "day": "03",
      "file": "2025/September/03.tsv",
      "date": "2025-09-03",
      "performance_90_day": 3.591879660309277,
      "performance_annualized": 55.96412653327341,
      "total_stocks": 20
    },
    {
      "year": "2025",
      "month": "September",
      "day": "04",
      "file": "2025/September/04.tsv",
      "date": "2025-09-04",
      "performance_90_day": -2.955754081392554,
      "performance_annualized": -32.387723276158255,
      "total_stocks": 20
    },
    {
      "year": "2025",
      "month": "September",
      "day": "05",
      "file": "2025/September/05.tsv",
      "date": "2025-09-05",
      "performance_90_day": -4.159611279905153,
      "performance_annualized": -43.71494328372314,
      "total_stocks": 20
    },
    {
      "year": "2025",
      "month": "September",
      "day": "06",
      "file": "2025/September/06.tsv",
      "date": "2025-09-06",
      "performance_90_day": 3.961432506279517,
      "performance_annualized": 72.5928250942349,
      "total_stocks": 20
    },
    {
      "year": "2025",
      "month": "September",
      "day": "07",
      "file": "2025/September/07.tsv",
      "date": "2025-09-07",
      "performance_90_day": -1.4769658336317446,
      "performance_annualized": -19.538719754590673,
      "total_stocks": 20
    },
    {
      "year": "2025",
      "month": "September",
      "day": "08",
      "file": "2025/September/08.tsv",
      "date": "2025-09-08",
      "performance_90_day": 4.376918779318755,
      "performance_annualized": 91.9273259417463,
      "total_stocks": 20
    },
    {
      "year": "2025",
      "month": "September",
      "day": "09",
      "file": "2025/September/09.tsv",
      "date": "2025-09-09",
      "performance_90_day": -2.854853586348008,
      "performance_annualized": -36.86913895999374,
      "total_stocks": 20
    },
    {
      "year": "2025",
      "month": "September",
      "day": "10",
      "file": "2025/September/10.tsv",
      "date": "2025-09-10",
      "performance_90_day": 1.761366331877659,
      "performance_annualized": 33.62689105015835,
      "total_stocks": 20
    },
    {
      "year": "2025",
      "month": "September",
      "day": "11",
      "file": "2025/September/11.tsv",
      "date": "2025-09-11",
      "performance_90_day": -3.7377491410019856,
      "performance_annualized": -48.44713725467794,
      "total_stocks": 20
    },
    {
      "year": "2025",
      "month": "September",
      "day": "12",
      "file": "2025/September/12.tsv",
      "date": "2025-09-12",
      "performance_90_day": 5.444362097086743,
      "performance_annualized": 163.3080772975825,
      "total_stocks": 20
    },
    {
      "year": "2025",
      "month": "September",
      "day": "13",
      "file": "2025/September/13.tsv",
      "date": "2025-09-13",
      "performance_90_day": 6.162828021352135,
      "performance_annualized": 215.7088338035398,
      "total_stocks": 20
    },
    {
      "year": "2025",
      "month": "September",
      "day": "14",
      "file": "2025/September/14.tsv",
      "date": "2025-09-14",
      "performance_90_day": -0.6650313293227816,
      "performance_annualized": -12.663058454761975,
      "total_stocks": 20
    },
    {
      "year": "2025",
      "month": "September",
      "day": "15",
      "file": "2025/September/15.tsv",
      "date": "2025-09-15",
      "performance_90_day": -0.6752592445803813,
      "performance_annualized": -13.547364543819064,
      "total_stocks": 20
    },
    {
      "year": "2025",
      "month": "September",
      "day": "16",
      "file": "2025/September/16.tsv",
      "date": "2025-09-16",
      "performance_90_day": 0.0739341618604085,
      "performance_annualized": 1.7014675080968988,
      "total_stocks": 20
    },
    {
      "year": "2025",
      "month": "September",
      "day": "17",
      "file": "2025/September/17.tsv",
      "date": "2025-09-17",
      "performance_90_day": -1.3389820422720102,
      "performance_annualized": -27.98131832548787,
      "total_stocks": 20
    },
    {
      "year": "2025",
      "month": "September",
      "day": "18",
      "file": "2025/September/18.tsv",
      "date": "2025-09-18",
      "performance_90_day": 1.5619774262503356,
      "performance_annualized": 49.834162575946415,
      "total_stocks": 20
    },
    {
      "year": "2025",
      "month": "September",
      "day": "19",
      "file": "2025/September/19.tsv",
      "date": "2025-09-19",
      "performance_90_day": 2.292719994852773,
      "performance_annualized": 89.05969735658444,
      "total_stocks": 20
    },
    {
      "year": "2025",
      "month": "September",
      "day": "20",
      "file": "2025/September/20.tsv",
      "date": "2025-09-20",
      "performance_90_day": 0.6454989586076643,
      "performance_annualized": 21.633512672453236,
      "total_stocks": 20
    },
    {
      "year": "2025",
      "month": "September",
      "day": "21",
      "file": "2025/September/21.tsv",
      "date": "2025-09-21",
      "performance_90_day": -1.17950029861581,
      "performance_annualized": -32.56296108711223,
      "total_stocks": 20
    },
    {
      "year": "2025",
      "month": "September",
      "day": "22",
      "file": "2025/September/22.tsv",
      "date": "2025-09-22",
      "performance_90_day": -1.6572173164934316,
      "performance_annualized": -45.68502922139345,
      "total_stocks": 20
    },
    {
      "year": "2025",
      "month": "September",
      "day": "23",
      "file": "2025/September/23.tsv",
      "date": "2025-09-23",
      "performance_90_day": -0.14736281653684652,
      "performance_annualized": -5.809310922863242,
      "total_stocks": 20
    },
    {
      "year": "2025",
      "month": "September",
      "day": "24",
      "file": "2025/September/24.tsv",
      "date": "2025-09-24",
      "performance_90_day": -0.9184870723450512,
      "performance_annualized": -34.37965828282782,
      "total_stocks": 20
    },
    {
      "year": "2025",
      "month": "September",
      "day": "25",
      "file": "2025/September/25.tsv",
      "date": "2025-09-25",
      "performance_90_day": -1.3484985364784443,
      "performance_annualized": -50.75757120264619,
      "total_stocks": 20
    },
    {
      "year": "2025",
      "month": "September",
      "day": "26",
      "file": "2025/September/26.tsv",
      "date": "2025-09-26",
      "performance_90_day": -0.731261347935896,
      "performance_annualized": -36.03223802082355,
      "total_stocks": 20
    },
    {
      "year": "2025",
      "month": "September",
      "day": "27",
      "file": "2025/September/27.tsv",
      "date": "2025-09-27",
      "performance_90_day": -1.340000982190341,
      "performance_annualized": -62.674309387937384,
      "total_stocks": 20
    },
    {
      "year": "2025",
      "month": "September",
      "day": "28",
      "file": "2025/September/28.tsv",
      "date": "2025-09-28",
      "performance_90_day": -1.1976965016265595,
      "performance_annualized": -66.72116809535306,
      "total_stocks": 20
    },
    {
      "year": "2025",
      "month": "September",
      "day": "29",
      "file": "2025/September/29.tsv",
      "date": "2025-09-29",
      "performance_90_day": -0.9735795197388644,
      "performance_annualized": -69.6125615469082,
      "total_stocks": 20
    },
    {
      "year": "2025",
      "month": "September",
      "day": "30",
      "file": "2025/September/30.tsv",
      "date": "2025-09-30",
      "performance_90_day": -0.8641383122770853,
      "performance_annualized": -79.50503121101818,
      "total_stocks": 20
    }
  ]
}