{
  "scores": [
    {
      "year": "2024",
      "month": "October",
      "day": "15",
      "file": "2024/October/15.tsv",
      "date": "2024-10-15",
      "performance_90_day": -10.596468152538296,
      "performance_annualized": -36.52816427941216,
      "total_stocks": 23
    },
    {
      "year": "2024",
      "month": "November",
      "day": "2",
      "file": "2024/November/2.tsv",
      "date": "2024-11-02",
      "performance_90_day": 0.47843554050118575,
      "performance_annualized": 1.9559028582294191,
      "total_stocks": 23
    },
    {
      "year": "2024",
      "month": "November",
      "day": "15",
      "file": "2024/November/15.tsv",
      "date": "2024-11-15",
      "performance_90_day": 6.070877750937328,
      "performance_annualized": 27.021653057772465,
      "total_stocks": 20
    },
    {
      "year": "2024",
      "month": "December",
      "day": "3",
      "file": "2024/December/3.tsv",
      "date": "2024-12-3",
      "performance_90_day": -12.97702160840258,
      "performance_annualized": -43.11281823170415,
      "total_stocks": 21
    },
    {
      "year": "2024",
      "month": "December",
      "day": "15",
      "file": "2024/December/15.tsv",
      "date": "2024-12-15",
      "performance_90_day": -6.5151151890413646,
      "performance_annualized": -24.15539972665488,
      "total_stocks": 20
    },
    {
      "year": "2024",
      "month": "December",
      "day": "29",
      "file": "2024/December/29.tsv",
      "date": "2024-12-29",
      "performance_90_day": 3.937749930489853,
      "performance_annualized": 17.175424906804192,
      "total_stocks": 23
    },
    {
      "year": "2025",
      "month": "January",
      "day": "6",
      "file": "2025/January/6.tsv",
      "date": "2025-01-06",
      "performance_90_day": -4.675630515830862,
      "performance_annualized": -18.024411969926433,
      "total_stocks": 21
    },
    {
      "year": "2025",
      "month": "January",
      "day": "15",
      "file": "2025/January/15.tsv",
      "date": "2025-01-15",
      "performance_90_day": -6.352873298042878,
      "performance_annualized": -23.38478866006396,
      "total_stocks": 20
    },
    {
      "year": "2025",
      "month": "February",
      "day": "5",
      "file": "2025/February/5.tsv",
      "date": "2025-02-05",
      "performance_90_day": 0.19559942408913636,
      "performance_annualized": 0.7955581694911729,
      "total_stocks": 23
    },
    {
      "year": "2025",
      "month": "February",
      "day": "15",
      "file": "2025/February/15.tsv",
      "date": "2025-02-15",
      "performance_90_day": 1.5599463207634314,
      "performance_annualized": 6.483420750536428,
      "total_stocks": 20
    },
    {
      "year": "2025",
      "month": "February",
      "day": "28",
      "file": "2025/February/28.tsv",
      "date": "2025-02-28",
      "performance_90_day": 0.5508766243813251,
      "performance_annualized": 2.254544892295063,
      "total_stocks": 23
    },
    {
      "year": "2025",
      "month": "March",
      "day": "5",
      "file": "2025/March/5.tsv",
      "date": "2025-03-05",
      "performance_90_day": -0.07045030355041249,
      "performance_annualized": -0.2856029516447811,
      "total_stocks": 20
    },
    {
      "year": "2025",
      "month": "March",
      "day": "12",
      "file": "2025/March/12.tsv",
      "date": "2025-03-12",
      "performance_90_day": 5.413003216398942,
      "performance_annualized": 23.854628344013463,
      "total_stocks": 22
    },
    {
      "year": "2025",
      "month": "March",
      "day": "21",
      "file": "2025/March/21.tsv",
      "date": "2025-03-21",
      "performance_90_day": 5.672681768671852,
      "performance_annualized": 25.412673143857667,
      "total_stocks": 21
    },
    {
      "year": "2025",
      "month": "April",
      "day": "4",
      "file": "2025/April/4.tsv",
      "date": "2025-04-04",
      "performance_90_day": 17.682088734710387,
      "performance_annualized": 93.62714581099452,
      "total_stocks": 20
    },
    {
      "year": "2025",
      "month": "April",
      "day": "15",
      "file": "2025/April/15.tsv",
      "date": "2025-04-15",
      "performance_90_day": 23.771358198646556,
      "performance_annualized": 137.620261331392,
      "total_stocks": 20
    },
    {
      "year": "2025",
      "month": "April",
      "day": "20",
      "file": "2025/April/20.tsv",
      "date": "2025-04-20",
      "performance_90_day": 27.898266829482147,
      "performance_annualized": 174.51454326382665,
      "total_stocks": 22
    },
    {
      "year": "2025",
      "month": "April",
      "day": "22",
      "file": "2025/April/22.tsv",
      "date": "2025-04-22",
      "performance_90_day": 23.636815765705272,
      "performance_annualized": 136.57373938336391,
      "total_stocks": 20
    },
    {
      "year": "2025",
      "month": "May",
      "day": "1",
      "file": "2025/May/1.tsv",
      "date": "2025-05-01",
      "performance_90_day": 0.0,
      "performance_annualized": 0.0,
      "total_stocks": 20
    },
    {
      "year": "2025",
      "month": "May",
      "day": "15",
      "file": "2025/May/15.tsv",
      "date": "2025-05-15",
      "performance_90_day": 0.0,
      "performance_annualized": 0.0,
      "total_stocks": 20
    },
    {
      "year": "2025",
      "month": "May",
      "day": "27",
      "file": "2025/May/27.tsv",
      "date": "2025-05-27",
      "performance_90_day": 0.0,
      "performance_annualized": 0.0,
      "total_stocks": 22
    },
    {
      "year": "2025",
      "month": "June",
      "day": "5",
      "file": "2025/June/05.tsv",
      "date": "2025-06-05",
      "performance_90_day": 0.0,
      "performance_annualized": 0.0,
      "total_stocks": 24
    },
    {
      "year": "2025",
      "month": "June",
      "day": "11",
      "file": "2025/June/11.tsv",
      "date": "2025-06-11",
      "performance_90_day": 0.0,
      "performance_annualized": 0.0,
      "total_stocks": 25
    },
    {
      "year": "2025",
      "month": "June",
      "day": "20",
      "file": "2025/June/20.tsv",
      "date": "2025-06-20",
      "performance_90_day": 0.0,
      "performance_annualized": 0.0,
      "total_stocks": 19
    },
    {
      "year": "2025",
      "month": "June",
      "day": "21",
      "file": "2025/June/21.tsv",
      "date": "2025-06-21",
      "performance_90_day": 0.0,
      "performance_annualized": 0.0,
      "total_stocks": 19
    },
    {
      "year": "2025",
      "month": "June",
      "day": "22",
      "file": "2025/June/22.tsv",
      "date": "2025-06-22",
      "performance_90_day": 0.0,
      "performance_annualized": 0.0,
      "total_stocks": 19
    },
    {
      "year": "2025",
      "month": "June",
      "day": "23",
      "file": "2025/June/23.tsv",
      "date": "2025-06-23",
      "performance_90_day": 0.0,
      "performance_annualized": 0.0,
      "total_stocks": 19
    },
    {
      "year": "2025",
      "month": "June",
      "day": "24",
      "file": "2025/June/24.tsv",
      "date": "2025-06-24",
      "performance_90_day": 0.0,
      "performance_annualized": 0.0,
      "total_stocks": 19
    },
    {
      "year": "2025",
      "month": "June",
      "day": "25",
      "file": "2025/June/25.tsv",
      "date": "2025-06-25",
      "performance_90_day": 0.0,
      "performance_annualized": 0.0,
      "total_stocks": 20
    },
    {
      "year": "2025",
      "month": "June",
      "day": "26",
      "file": "2025/June/26.tsv",
      "date": "2025-06-26",
      "performance_90_day": 0.0,
      "performance_annualized": 0.0,
      "total_stocks": 20
    },
    {
      "year": "2025",
      "month": "June",
      "day": "27",
      "file": "2025/June/27.tsv",
      "date": "2025-06-27",
      "performance_90_day": 0.0,
      "performance_annualized": 0.0,
      "total_stocks": 20
    },
    {
      "year": "2025",
      "month": "June",
      "day": "28",
      "file": "2025/June/28.tsv",
      "date": "2025-06-28",
      "performance_90_day": 0.0,
      "performance_annualized": 0.0,
      "total_stocks": 20
    },
    {
      "year": "2025",
      "month": "June",
      "day": "29",
      "file": "2025/June/29.tsv",
      "date": "2025-06-29",
      "performance_90_day": 0.0,
      "performance_annualized": 0.0,
      "total_stocks": 20
    },
    {
      "year": "2025",
      "month": "June",
      "day": "30",
      "file": "2025/June/30.tsv",
      "date": "2025-06-30",
      "performance_90_day": 0.0,
      "performance_annualized": 0.0,
      "total_stocks": 20
    },
    {
      "year": "2025",
      "month": "July",
      "day": "01",
      "file": "2025/July/01.tsv",
      "date": "2025-07-01",
      "performance_90_day": 0.0,
      "performance_annualized": 0.0,
      "total_stocks": 20
    },
    {
      "year": "2025",
      "month": "July",
      "day": "02",
      "file": "2025/July/02.tsv",
      "date": "2025-07-02",
      "performance_90_day": 0.0,
      "performance_annualized": 0.0,
      "total_stocks": 20
    },
    {
      "year": "2025",
      "month": "July",
      "day": "03",
      "file": "2025/July/03.tsv",
      "date": "2025-07-03",
      "performance_90_day": 0.0,
      "performance_annualized": 0.0,
      "total_stocks": 20
    },
    {
      "year": "2025",
      "month": "July",
      "day": "04",
      "file": "2025/July/04.tsv",
      "date": "2025-07-04",
      "performance_90_day": 0.0,
      "performance_annualized": 0.0,
      "total_stocks": 20
    },
    {
      "year": "2025",
      "month": "July",
      "day": "05",
      "file": "2025/July/05.tsv",
      "date": "2025-07-05",
      "performance_90_day": 0.0,
      "performance_annualized": 0.0,
      "total_stocks": 20
    },
    {
      "year": "2025",
      "month": "July",
      "day": "06",
      "file": "2025/July/06.tsv",
      "date": "2025-07-06",
      "performance_90_day": 0.0,
      "performance_annualized": 0.0,
      "total_stocks": 20
    },
    {
      "year": "2025",
      "month": "July",
      "day": "07",
      "file": "2025/July/07.tsv",
      "date": "2025-07-07",
      "performance_90_day": 0.0,
      "performance_annualized": 0.0,
      "total_stocks": 20
    },
    {
      "year": "2025",
      "month": "July",
      "day": "10",
      "file": "2025/July/10.tsv",
      "date": "2025-07-10",
      "performance_90_day": 0.0,
      "performance_annualized": 0.0,
      "total_stocks": 20
    },
    {
      "year": "2025",
      "month": "July",
      "day": "11",
      "file": "2025/July/11.tsv",
      "date": "2025-07-11",
      "performance_90_day": 0.0,
      "performance_annualized": 0.0,
      "total_stocks": 20
    },
    {
      "year": "2025",
      "month": "July",
      "day": "12",
      "file": "2025/July/12.tsv",
      "date": "2025-07-12",
      "performance_90_day": 0.0,
      "performance_annualized": 0.0,
      "total_stocks": 20
    },
    {
      "year": "2025",
      "month": "July",
      "day": "13",
      "file": "2025/July/13.tsv",
      "date": "2025-07-13",
      "performance_90_day": 0.0,
      "performance_annualized": 0.0,
      "total_stocks": 20
    },
    {
      "year": "2025",
      "month": "July",
      "day": "14",
      "file": "2025/July/14.tsv",
      "date": "2025-07-14",
      "performance_90_day": 0.0,
      "performance_annualized": 0.0,
      "total_stocks": 20
    },
    {
      "year": "2025",
      "month": "July",
      "day": "15",
      "file": "2025/July/15.tsv",
      "date": "2025-07-15",
      "performance_90_day": 0.0,
      "performance_annualized": 0.0,
      "total_stocks": 20
    },
    {
      "year": "2025",
      "month": "July",
      "day": "16",
      "file": "2025/July/16.tsv",
      "date": "2025-07-16",
      "performance_90_day": 0.0,
      "performance_annualized": 0.0,
      "total_stocks": 20
    },
    {
      "year": "2025",
      "month": "July",
      "day": "17",
      "file": "2025/July/17.tsv",
      "date": "2025-07-17",
      "performance_90_day": 0.0,
      "performance_annualized": 0.0,
      "total_stocks": 20
    },
    {
      "year": "2025",
      "month": "July",
      "day": "18",
      "file": "2025/July/18.tsv",
      "date": "2025-07-18",
      "performance_90_day": 0.0,
      "performance_annualized": 0.0,
      "total_stocks": 20
    },
    {
      "year": "2025",
      "month": "July",
      "day": "19",
      "file": "2025/July/19.tsv",
      "date": "2025-07-19",
      "performance_90_day": 0.0,
      "performance_annualized": 0.0,
      "total_stocks": 20
    },
    {
      "year": "2025",
      "month": "July",
      "day": "20",
      "file": "2025/July/20.tsv",
      "date": "2025-07-20",
      "performance_90_day": 0.0,
      "performance_annualized": 0.0,
      "total_stocks": 20
    },
    {
      "year": "2025",
      "month": "July",
      "day": "21",
      "file": "2025/July/21.tsv",
      "date": "2025-07-21",
      "performance_90_day": 0.0,
      "performance_annualized": 0.0,
      "total_stocks": 20
    },
    {
      "year": "2025",
      "month": "July",
      "day": "22",
      "file": "2025/July/22.tsv",
      "date": "2025-07-22",
      "performance_90_day": 0.0,
      "performance_annualized": 0.0,
      "total_stocks": 20
    },
    {
      "year": "2025",
      "month": "July",
      "day": "23",
      "file": "2025/July/23.tsv",
      "date": "2025-07-23",
      "performance_90_day": 0.0,
      "performance_annualized": 0.0,
      "total_stocks": 20
    },
    {
      "year": "2025",
      "month": "July",
      "day": "24",
      "file": "2025/July/24.tsv",
      "date": "2025-07-24",
      "performance_90_day": 0.0,
      "performance_annualized": 0.0,
      "total_stocks": 20
    },
    {
      "year": "2025",
      "month": "July",
      "day": "25",
      "file": "2025/July/25.tsv",
      "date": "2025-07-25",
      "performance_90_day": 0.0,
      "performance_annualized": 0.0,
      "total_stocks": 20
    },
    {
      "year": "2025",
      "month": "July",
      "day": "26",
      "file": "2025/July/26.tsv",
      "date": "2025-07-26",
      "performance_90_day": 0.0,
      "performance_annualized": 0.0,
      "total_stocks": 20
    },
    {
      "year": "2025",
      "month": "July",
      "day": "27",
      "file": "2025/July/27.tsv",
      "date": "2025-07-27",
      "performance_90_day": 0.0,
      "performance_annualized": 0.0,
      "total_stocks": 20
    },
    {
      "year": "2025",
      "month": "July",
      "day": "28",
      "file": "2025/July/28.tsv",
      "date": "2025-07-28",
      "performance_90_day": 0.0,
      "performance_annualized": 0.0,
      "total_stocks": 20
    },
    {
      "year": "2025",
      "month": "July",
      "day": "29",
      "file": "2025/July/29.tsv",
      "date": "2025-07-29",
      "performance_90_day": 0.0,
      "performance_annualized": 0.0,
      "total_stocks": 20
    },
    {
      "year": "2025",
      "month": "July",
      "day": "30",
      "file": "2025/July/30.tsv",
      "date": "2025-07-30",
      "performance_90_day": 0.0,
      "performance_annualized": 0.0,
      "total_stocks": 20
    },
    {
      "year": "2025",
      "month": "July",
      "day": "31",
      "file": "2025/July/31.tsv",
      "date": "2025-07-31",
      "performance_90_day": 0.0,
      "performance_annualized": 0.0,
      "total_stocks": 20
    },
    {
      "year": "2025",
      "month": "August",
      "day": "01",
      "file": "2025/August/01.tsv",
      "date": "2025-08-01",
      "performance_90_day": 0.0,
      "performance_annualized": 0.0,
      "total_stocks": 20
    },
    {
      "year": "2025",
      "month": "August",
      "day": "02",
      "file": "2025/August/02.tsv",
      "date": "2025-08-02",
      "performance_90_day": 0.0,
      "performance_annualized": 0.0,
      "total_stocks": 20
    },
    {
      "year": "2025",
      "month": "August",
      "day": "03",
      "file": "2025/August/03.tsv",
      "date": "2025-08-03",
      "performance_90_day": 0.0,
      "performance_annualized": 0.0,
      "total_stocks": 20
    },
    {
      "year": "2025",
      "month": "August",
      "day": "08",
      "file": "2025/August/08.tsv",
      "date": "2025-08-08",
      "performance_90_day": 0.0,
      "performance_annualized": 0.0,
      "total_stocks": 20
    },
    {
      "year": "2025",
      "month": "August",
      "day": "09",
      "file": "2025/August/09.tsv",
      "date": "2025-08-09",
      "performance_90_day": 0.0,
      "performance_annualized": 0.0,
      "total_stocks": 20
    },
    {
      "year": "2025",
      "month": "August",
      "day": "10",
      "file": "2025/August/10.tsv",
      "date": "2025-08-10"
    },
    {
      "year": "2025",
      "month": "August",
      "day": "11",
      "file": "2025/August/11.tsv",
      "date": "2025-08-11"
    },
    {
      "year": "2025",
      "month": "August",
      "day": "12",
      "file": "2025/August/12.tsv",
      "date": "2025-08-12"
    },
    {
      "year": "2025",
      "month": "August",
      "day": "13",
      "file": "2025/August/13.tsv",
      "date": "2025-08-13"
    },
    {
      "year": "2025",
      "month": "August",
      "day": "14",
      "file": "2025/August/14.tsv",
      "date": "2025-08-14"
    },
    {
      "year": "2025",
      "month": "August",
      "day": "15",
      "file": "2025/August/15.tsv",
      "date": "2025-08-15"
    },
    {
      "year": "2025",
      "month": "August",
      "day": "16",
      "file": "2025/August/16.tsv",
      "date": "2025-08-16"
    },
    {
      "year": "2025",
      "month": "August",
      "day": "17",
      "file": "2025/August/17.tsv",
      "date": "2025-08-17"
    },
    {
      "year": "2025",
      "month": "August",
      "day": "18",
      "file": "2025/August/18.tsv",
      "date": "2025-08-18"
    },
    {
      "year": "2025",
      "month": "August",
      "day": "19",
      "file": "2025/August/19.tsv",
      "date": "2025-08-19"
    },
    {
      "year": "2025",
      "month": "August",
      "day": "20",
      "file": "2025/August/20.tsv",
      "date": "2025-08-20",
      "performance_90_day": 0.0,
      "performance_annualized": 0.0,
      "total_stocks": 20
    },
    {
      "year": "2025",
      "month": "August",
      "day": "21",
      "file": "2025/August/21.tsv",
      "date": "2025-08-21",
      "performance_90_day": 0.0,
      "performance_annualized": 0.0,
      "total_stocks": 20
    },
    {
      "year": "2025",
      "month": "August",
      "day": "22",
      "file": "2025/August/22.tsv",
      "date": "2025-08-22",
      "performance_90_day": 0.0,
      "performance_annualized": 0.0,
      "total_stocks": 20
    },
    {
      "year": "2025",
      "month": "August",
      "day": "23",
      "file": "2025/August/23.tsv",
      "date": "2025-08-23",
      "performance_90_day": 0.0,
      "performance_annualized": 0.0,
      "total_stocks": 20
    },
    {
      "year": "2025",
      "month": "August",
      "day": "24",
      "file": "2025/August/24.tsv",
      "date": "2025-08-24",
      "performance_90_day": 0.0,
      "performance_annualized": 0.0,
      "total_stocks": 20
    },
    {
      "year": "2025",
      "month": "August",
      "day": "25",
      "file": "2025/August/25.tsv",
      "date": "2025-08-25",
      "performance_90_day": 0.0,
      "performance_annualized": 0.0,
      "total_stocks": 20
    },
    {
      "year": "2025",
      "month": "August",
      "day": "26",
      "file": "2025/August/26.tsv",
      "date": "2025-08-26",
      "performance_90_day": 0.0,
      "performance_annualized": 0.0,
      "total_stocks": 20
    },
    {
      "year": "2025",
      "month": "August",
      "day": "27",
      "file": "2025/August/27.tsv",
      "date": "2025-08-27",
      "performance_90_day": 0.0,
      "performance_annualized": 0.0,
      "total_stocks": 20
    },
    {
      "year": "2025",
      "month": "August",
      "day": "29",
      "file": "2025/August/29.tsv",
      "date": "2025-08-29",
      "performance_90_day": 0.0,
      "performance_annualized": 0.0,
      "total_stocks": 20
    },
    {
      "year": "2025",
      "month": "August",
      "day": "30",
      "file": "2025/August/30.tsv",
      "date": "2025-08-30",
      "performance_90_day": 0.0,
      "performance_annualized": 0.0,
      "total_stocks": 20
    },
    {
      "year": "2025",
      "month": "August",
      "day": "31",
      "file": "2025/August/31.tsv",
      "date": "2025-08-31",
      "performance_90_day": 0.0,
      "performance_annualized": 0.0,
      "total_stocks": 20
    },
    {
      "year": "2025",
      "month": "September",
      "day": "01",
      "file": "2025/September/01.tsv",
      "date": "2025-09-01",
      "performance_90_day": 0.0,
      "performance_annualized": 0.0,
      "total_stocks": 20
    },
    {
      "year": "2025",
      "month": "September",
      "day": "02",
      "file": "2025/September/02.tsv",
      "date": "2025-09-02",
      "performance_90_day": 0.0,
      "performance_annualized": 0.0,
      "total_stocks": 20
    },
    {
      "year": "2025",
      "month": "September",
      "day": "03",
      "file": "2025/September/03.tsv",
      "date": "2025-09-03",
      "performance_90_day": 0.0,
      "performance_annualized": 0.0,
      "total_stocks": 20
    },
    {
      "year": "2025",
      "month": "September",
      "day": "04",
      "file": "2025/September/04.tsv",
      "date": "2025-09-04",
      "performance_90_day": 0.0,
      "performance_annualized": 0.0,
      "total_stocks": 20
    },
    {
      "year": "2025",
      "month": "September",
      "day": "05",
      "file": "2025/September/05.tsv",
      "date": "2025-09-05",
      "performance_90_day": 0.0,
      "performance_annualized": 0.0,
      "total_stocks": 20
    },
    {
      "year": "2025",
      "month": "September",
      "day": "06",
      "file": "2025/September/06.tsv",
      "date": "2025-09-06",
      "performance_90_day": 0.0,
      "performance_annualized": 0.0,
      "total_stocks": 20
    },
    {
      "year": "2025",
      "month": "September",
      "day": "07",
      "file": "2025/September/07.tsv",
      "date": "2025-09-07",
      "performance_90_day": 0.0,
      "performance_annualized": 0.0,
      "total_stocks": 20
    },
    {
      "year": "2025",
      "month": "September",
      "day": "08",
      "file": "2025/September/08.tsv",
      "date": "2025-09-08",
      "performance_90_day": 0.0,
      "performance_annualized": 0.0,
      "total_stocks": 20
    },
    {
      "year": "2025",
      "month": "September",
      "day": "09",
      "file": "2025/September/09.tsv",
      "date": "2025-09-09",
      "performance_90_day": 0.0,
      "performance_annualized": 0.0,
      "total_stocks": 20
    },
    {
      "year": "2025",
      "month": "September",
      "day": "10",
      "file": "2025/September/10.tsv",
      "date": "2025-09-10",
      "performance_90_day": 0.0,
      "performance_annualized": 0.0,
      "total_stocks": 20
    },
    {
      "year": "2025",
      "month": "September",
      "day": "11",
      "file": "2025/September/11.tsv",
      "date": "2025-09-11",
      "performance_90_day": 0.0,
      "performance_annualized": 0.0,
      "total_stocks": 20
    },
    {
      "year": "2025",
      "month": "September",
      "day": "12",
      "file": "2025/September/12.tsv",
      "date": "2025-09-12",
      "performance_90_day": 0.0,
      "performance_annualized": 0.0,
      "total_stocks": 20
    },
    {
      "year": "2025",
      "month": "September",
      "day": "13",
      "file": "2025/September/13.tsv",
      "date": "2025-09-13",
      "performance_90_day": 0.0,
      "performance_annualized": 0.0,
      "total_stocks": 20
    },
    {
      "year": "2025",
      "month": "September",
      "day": "14",
      "file": "2025/September/14.tsv",
      "date": "2025-09-14",
      "performance_90_day": 0.0,
      "performance_annualized": 0.0,
      "total_stocks": 20
    },
    {
      "year": "2025",
      "month": "September",
      "day": "15",
      "file": "2025/September/15.tsv",
      "date": "2025-09-15",
      "performance_90_day": 0.0,
      "performance_annualized": 0.0,
      "total_stocks": 20
    },
    {
      "year": "2025",
      "month": "September",
      "day": "16",
      "file": "2025/September/16.tsv",
      "date": "2025-09-16",
      "performance_90_day": 0.0,
      "performance_annualized": 0.0,
      "total_stocks": 20
    },
    {
      "year": "2025",
      "month": "September",
      "day": "17",
      "file": "2025/September/17.tsv",
      "date": "2025-09-17",
      "performance_90_day": 0.0,
      "performance_annualized": 0.0,
      "total_stocks": 20
    },
    {
      "year": "2025",
      "month": "September",
      "day": "18",
      "file": "2025/September/18.tsv",
      "date": "2025-09-18",
      "performance_90_day": 0.0,
      "performance_annualized": 0.0,
      "total_stocks": 20
    },
    {
      "year": "2025",
      "month": "September",
      "day": "19",
      "file": "2025/September/19.tsv",
      "date": "2025-09-19",
      "performance_90_day": 0.0,
      "performance_annualized": 0.0,
      "total_stocks": 20
    },
    {
      "year": "2025",
      "month": "September",
      "day": "20",
      "file": "2025/September/20.tsv",
      "date": "2025-09-20",
      "performance_90_day": 0.0,
      "performance_annualized": 0.0,
      "total_stocks": 20
    },
    {
      "year": "2025",
      "month": "September",
      "day": "21",
      "file": "2025/September/21.tsv",
      "date": "2025-09-21",
      "performance_90_day": 0.0,
      "performance_annualized": 0.0,
      "total_stocks": 20
    },
    {
      "year": "2025",
      "month": "September",
      "day": "22",
      "file": "2025/September/22.tsv",
      "date": "2025-09-22",
      "performance_90_day": 0.0,
      "performance_annualized": 0.0,
      "total_stocks": 20
    },
    {
      "year": "2025",
      "month": "September",
      "day": "23",
      "file": "2025/September/23.tsv",
      "date": "2025-09-23",
      "performance_90_day": 0.0,
      "performance_annualized": 0.0,
      "total_stocks": 20
    },
    {
      "year": "2025",
      "month": "September",
      "day": "24",
      "file": "2025/September/24.tsv",
      "date": "2025-09-24",
      "performance_90_day": 0.0,
      "performance_annualized": 0.0,
      "total_stocks": 20
    },
    {
      "year": "2025",
      "month": "September",
      "day": "25",
      "file": "2025/September/25.tsv",
      "date": "2025-09-25",
      "performance_90_day": 0.0,
      "performance_annualized": 0.0,
      "total_stocks": 20
    },
    {
      "year": "2025",
      "month": "September",
      "day": "26",
      "file": "2025/September/26.tsv",
      "date": "2025-09-26",
      "performance_90_day": 0.0,
      "performance_annualized": 0.0,
      "total_stocks": 20
    },
    {
      "year": "2025",
      "month": "September",
      "day": "27",
      "file": "2025/September/27.tsv",
      "date": "2025-09-27",
      "performance_90_day": 0.0,
      "performance_annualized": 0.0,
      "total_stocks": 20
    },
    {
      "year": "2025",
      "month": "September",
      "day": "28",
      "file": "2025/September/28.tsv",
      "date": "2025-09-28",
      "performance_90_day": 0.0,
      "performance_annualized": 0.0,
      "total_stocks": 20
    },
    {
      "year": "2025",
      "month": "September",
      "day": "29",
      "file": "2025/September/29.tsv",
      "date": "2025-09-29",
      "performance_90_day": 0.0,
      "performance_annualized": 0.0,
      "total_stocks": 20
    },
    {
      "year": "2025",
      "month": "September",
      "day": "30",
      "file": "2025/September/30.tsv",
      "date": "2025-09-30",
      "performance_90_day": 0.0,
      "performance_annualized": 0.0,
      "total_stocks": 20
    },
    {
      "year": "2025",
      "month": "October",
      "day": "06",
      "file": "2025/October/06.tsv",
      "date": "2025-10-06",
      "performance_90_day": 0.0,
      "performance_annualized": 0.0,
      "total_stocks": 20
    },
    {
      "year": "2025",
      "month": "October",
      "day": "07",
      "file": "2025/October/07.tsv",
      "date": "2025-10-07",
      "performance_90_day": 0.0,
      "performance_annualized": 0.0,
      "total_stocks": 20
    },
    {
      "year": "2025",
      "month": "October",
      "day": "08",
      "file": "2025/October/08.tsv",
      "date": "2025-10-08",
      "performance_90_day": 0.0,
      "performance_annualized": 0.0,
      "total_stocks": 20
    },
    {
      "year": "2025",
      "month": "October",
      "day": "09",
      "file": "2025/October/09.tsv",
      "date": "2025-10-09",
      "performance_90_day": 0.0,
      "performance_annualized": 0.0,
      "total_stocks": 20
    },
    {
      "year": "2025",
      "month": "October",
      "day": "10",
      "file": "2025/October/10.tsv",
      "date": "2025-10-10",
      "performance_90_day": 0.0,
      "performance_annualized": 0.0,
      "total_stocks": 20
    },
    {
      "year": "2025",
      "month": "October",
      "day": "11",
      "file": "2025/October/11.tsv",
      "date": "2025-10-11",
      "performance_90_day": 0.0,
      "performance_annualized": 0.0,
      "total_stocks": 20
    },
    {
      "year": "2025",
      "month": "October",
      "day": "12",
      "file": "2025/October/12.tsv",
      "date": "2025-10-12",
      "performance_90_day": 0.0,
      "performance_annualized": 0.0,
      "total_stocks": 20
    },
    {
      "year": "2025",
      "month": "October",
      "day": "13",
      "file": "2025/October/13.tsv",
      "date": "2025-10-13",
      "performance_90_day": 0.0,
      "performance_annualized": 0.0,
      "total_stocks": 20
    },
    {
      "year": "2025",
      "month": "October",
      "day": "14",
      "file": "2025/October/14.tsv",
      "date": "2025-10-14",
      "performance_90_day": 0.0,
      "performance_annualized": 0.0,
      "total_stocks": 20
    },
    {
      "year": "2025",
      "month": "October",
      "day": "15",
      "file": "2025/October/15.tsv",
      "date": "2025-10-15",
      "performance_90_day": 0.0,
      "performance_annualized": 0.0,
      "total_stocks": 20
    },
    {
      "year": "2025",
      "month": "October",
      "day": "16",
      "file": "2025/October/16.tsv",
      "date": "2025-10-16",
      "performance_90_day": 0.0,
      "performance_annualized": 0.0,
      "total_stocks": 20
    },
    {
      "year": "2025",
      "month": "October",
      "day": "17",
      "file": "2025/October/17.tsv",
      "date": "2025-10-17",
      "performance_90_day": 0.0,
      "performance_annualized": 0.0,
      "total_stocks": 20
    },
    {
      "year": "2025",
      "month": "October",
      "day": "18",
      "file": "2025/October/18.tsv",
      "date": "2025-10-18",
      "performance_90_day": 0.0,
      "performance_annualized": 0.0,
      "total_stocks": 20
    },
    {
      "year": "2025",
      "month": "October",
      "day": "19",
      "file": "2025/October/19.tsv",
      "date": "2025-10-19",
      "performance_90_day": 0.0,
      "performance_annualized": 0.0,
      "total_stocks": 20
    },
    {
      "year": "2025",
      "month": "October",
      "day": "20",
      "file": "2025/October/20.tsv",
      "date": "2025-10-20",
      "performance_90_day": 0.0,
      "performance_annualized": 0.0,
      "total_stocks": 20
    },
    {
      "year": "2025",
      "month": "October",
      "day": "21",
      "file": "2025/October/21.tsv",
      "date": "2025-10-21",
      "performance_90_day": 0.0,
      "performance_annualized": 0.0,
      "total_stocks": 20
    },
    {
      "year": "2025",
      "month": "October",
      "day": "22",
      "file": "2025/October/22.tsv",
      "date": "2025-10-22",
      "performance_90_day": 0.0,
      "performance_annualized": 0.0,
      "total_stocks": 20
    },
    {
      "year": "2025",
      "month": "October",
      "day": "23",
      "file": "2025/October/23.tsv",
      "date": "2025-10-23",
      "performance_90_day": 0.0,
      "performance_annualized": 0.0,
      "total_stocks": 20
    },
    {
      "year": "2025",
      "month": "October",
      "day": "24",
      "file": "2025/October/24.tsv",
      "date": "2025-10-24",
      "performance_90_day": 0.0,
      "performance_annualized": 0.0,
      "total_stocks": 20
    },
    {
      "year": "2025",
      "month": "October",
      "day": "25",
      "file": "2025/October/25.tsv",
      "date": "2025-10-25",
      "performance_90_day": 0.0,
      "performance_annualized": 0.0,
      "total_stocks": 20
    },
    {
      "year": "2025",
      "month": "October",
      "day": "26",
      "file": "2025/October/26.tsv",
      "date": "2025-10-26",
      "performance_90_day": 0.0,
      "performance_annualized": 0.0,
      "total_stocks": 20
    },
    {
      "year": "2025",
      "month": "October",
      "day": "27",
      "file": "2025/October/27.tsv",
      "date": "2025-10-27",
      "performance_90_day": 0.0,
      "performance_annualized": 0.0,
      "total_stocks": 20
    },
    {
      "year": "2025",
      "month": "October",
      "day": "29",
      "file": "2025/October/29.tsv",
      "date": "2025-10-29",
      "performance_90_day": 0.0,
      "performance_annualized": 0.0,
      "total_stocks": 20
    },
    {
      "year": "2025",
      "month": "October",
      "day": "30",
      "file": "2025/October/30.tsv",
      "date": "2025-10-30",
      "performance_90_day": 0.0,
      "performance_annualized": 0.0,
      "total_stocks": 20
    },
    {
      "year": "2025",
      "month": "October",
      "day": "31",
      "file": "2025/October/31.tsv",
      "date": "2025-10-31",
      "performance_90_day": 0.0,
      "performance_annualized": 0.0,
      "total_stocks": 20
    },
    {
      "year": "2025",
      "month": "November",
      "day": "01",
      "file": "2025/November/01.tsv",
      "date": "2025-11-01",
      "performance_90_day": 0.0,
      "performance_annualized": 0.0,
      "total_stocks": 20
    },
    {
      "year": "2025",
      "month": "November",
      "day": "02",
      "file": "2025/November/02.tsv",
      "date": "2025-11-02",
      "performance_90_day": 0.0,
      "performance_annualized": 0.0,
      "total_stocks": 20
    },
    {
      "year": "2025",
      "month": "November",
      "day": "03",
      "file": "2025/November/03.tsv",
      "date": "2025-11-03",
      "performance_90_day": 0.0,
      "performance_annualized": 0.0,
      "total_stocks": 20
    },
    {
      "year": "2025",
      "month": "November",
      "day": "04",
      "file": "2025/November/04.tsv",
      "date": "2025-11-04",
      "performance_90_day": 0.0,
      "performance_annualized": 0.0,
      "total_stocks": 20
    },
    {
      "year": "2025",
      "month": "November",
      "day": "05",
      "file": "2025/November/05.tsv",
      "date": "2025-11-05",
      "performance_90_day": 0.0,
      "performance_annualized": 0.0,
      "total_stocks": 20
    },
    {
      "year": "2025",
      "month": "November",
      "day": "06",
      "file": "2025/November/06.tsv",
      "date": "2025-11-06",
      "performance_90_day": 0.0,
      "performance_annualized": 0.0,
      "total_stocks": 20
    },
    {
      "year": "2025",
      "month": "November",
      "day": "07",
      "file": "2025/November/07.tsv",
      "date": "2025-11-07",
      "performance_90_day": 0.0,
      "performance_annualized": 0.0,
      "total_stocks": 20
    },
    {
      "year": "2025",
      "month": "November",
      "day": "08",
      "file": "2025/November/08.tsv",
      "date": "2025-11-08",
      "performance_90_day": 0.0,
      "performance_annualized": 0.0,
      "total_stocks": 20
    },
    {
      "year": "2025",
      "month": "November",
      "day": "09",
      "file": "2025/November/09.tsv",
      "date": "2025-11-09",
      "performance_90_day": 0.0,
      "performance_annualized": 0.0,
      "total_stocks": 20
    },
    {
      "year": "2025",
      "month": "November",
      "day": "10",
      "file": "2025/November/10.tsv",
      "date": "2025-11-10",
      "performance_90_day": 0.0,
      "performance_annualized": 0.0,
      "total_stocks": 20
    },
    {
      "year": "2025",
      "month": "November",
      "day": "11",
      "file": "2025/November/11.tsv",
      "date": "2025-11-11",
      "performance_90_day": 0.0,
      "performance_annualized": 0.0,
      "total_stocks": 20
    },
    {
      "year": "2025",
      "month": "November",
      "day": "12",
      "file": "2025/November/12.tsv",
      "date": "2025-11-12",
      "performance_90_day": 0.0,
      "performance_annualized": 0.0,
      "total_stocks": 20
    },
    {
      "year": "2025",
      "month": "November",
      "day": "13",
      "file": "2025/November/13.tsv",
      "date": "2025-11-13",
      "performance_90_day": 0.0,
      "performance_annualized": 0.0,
      "total_stocks": 20
    },
    {
      "year": "2025",
      "month": "November",
      "day": "14",
      "file": "2025/November/14.tsv",
      "date": "2025-11-14",
      "performance_90_day": 0.0,
      "performance_annualized": 0.0,
      "total_stocks": 20
    },
    {
      "year": "2025",
      "month": "November",
      "day": "15",
      "file": "2025/November/15.tsv",
      "date": "2025-11-15",
      "performance_90_day": 0.0,
      "performance_annualized": 0.0,
      "total_stocks": 20
    },
    {
      "year": "2025",
      "month": "November",
      "day": "17",
      "file": "2025/November/17.tsv",
      "date": "2025-11-17",
      "performance_90_day": 0.0,
      "performance_annualized": 0.0,
      "total_stocks": 20
    },
    {
      "year": "2025",
      "month": "November",
      "day": "18",
      "file": "2025/November/18.tsv",
      "date": "2025-11-18",
      "performance_90_day": 0.0,
      "performance_annualized": 0.0,
      "total_stocks": 20
    },
    {
      "year": "2025",
      "month": "November",
      "day": "19",
      "file": "2025/November/19.tsv",
      "date": "2025-11-19",
      "performance_90_day": 0.0,
      "performance_annualized": 0.0,
      "total_stocks": 20
    },
    {
      "year": "2025",
      "month": "November",
      "day": "20",
      "file": "2025/November/20.tsv",
      "date": "2025-11-20",
      "performance_90_day": 0.0,
      "performance_annualized": 0.0,
      "total_stocks": 20
    },
    {
      "year": "2025",
      "month": "November",
      "day": "21",
      "file": "2025/November/21.tsv",
      "date": "2025-11-21",
      "performance_90_day": 0.0,
      "performance_annualized": 0.0,
      "total_stocks": 20
    },
    {
      "year": "2025",
      "month": "November",
      "day": "22",
      "file": "2025/November/22.tsv",
      "date": "2025-11-22",
      "performance_90_day": 0.0,
      "performance_annualized": 0.0,
      "total_stocks": 20
    },
    {
      "year": "2025",
      "month": "November",
      "day": "23",
      "file": "2025/November/23.tsv",
      "date": "2025-11-23",
      "performance_90_day": 0.0,
      "performance_annualized": 0.0,
      "total_stocks": 20
    },
    {
      "year": "2025",
      "month": "November",
      "day": "24",
      "file": "2025/November/24.tsv",
      "date": "2025-11-24",
      "performance_90_day": 0.0,
      "performance_annualized": 0.0,
      "total_stocks": 20
    },
    {
      "year": "2025",
      "month": "November",
      "day": "25",
      "file": "2025/November/25.tsv",
      "date": "2025-11-25",
      "performance_90_day": 0.0,
      "performance_annualized": 0.0,
      "total_stocks": 20
    },
    {
      "year": "2025",
      "month": "November",
      "day": "26",
      "file": "2025/November/26.tsv",
      "date": "2025-11-26",
      "performance_90_day": 0.0,
      "performance_annualized": 0.0,
      "total_stocks": 20
    },
    {
      "year": "2025",
      "month": "November",
      "day": "27",
      "file": "2025/November/27.tsv",
      "date": "2025-11-27",
      "performance_90_day": 0.0,
      "performance_annualized": 0.0,
      "total_stocks": 20
    },
    {
      "year": "2025",
      "month": "November",
      "day": "28",
      "file": "2025/November/28.tsv",
      "date": "2025-11-28",
      "performance_90_day": 0.0,
      "performance_annualized": 0.0,
      "total_stocks": 20
    },
    {
      "year": "2025",
      "month": "November",
      "day": "29",
      "file": "2025/November/29.tsv",
      "date": "2025-11-29",
      "performance_90_day": 0.0,
      "performance_annualized": 0.0,
      "total_stocks": 20
    },
    {
      "year": "2025",
      "month": "November",
      "day": "30",
      "file": "2025/November/30.tsv",
      "date": "2025-11-30",
      "performance_90_day": 0.0,
      "performance_annualized": 0.0,
      "total_stocks": 20
    },
    {
      "year": "2025",
      "month": "December",
      "day": "01",
      "file": "2025/December/01.tsv",
      "date": "2025-12-01",
      "performance_90_day": 0.0,
      "performance_annualized": 0.0,
      "total_stocks": 20
    },
    {
      "year": "2025",
      "month": "December",
      "day": "02",
      "file": "2025/December/02.tsv",
      "date": "2025-12-02",
      "performance_90_day": 0.0,
      "performance_annualized": 0.0,
      "total_stocks": 20
    },
    {
      "year": "2025",
      "month": "December",
      "day": "03",
      "file": "2025/December/03.tsv",
      "date": "2025-12-03",
      "performance_90_day": 0.0,
      "performance_annualized": 0.0,
      "total_stocks": 20
    },
    {
      "year": "2025",
      "month": "December",
      "day": "04",
      "file": "2025/December/04.tsv",
      "date": "2025-12-04",
      "performance_90_day": 0.0,
      "performance_annualized": 0.0,
      "total_stocks": 20
    },
    {
      "year": "2025",
      "month": "December",
      "day": "05",
      "file": "2025/December/05.tsv",
      "date": "2025-12-05",
      "performance_90_day": 0.0,
      "performance_annualized": 0.0,
      "total_stocks": 20
    },
    {
      "year": "2025",
      "month": "December",
      "day": "06",
      "file": "2025/December/06.tsv",
      "date": "2025-12-06",
      "performance_90_day": 0.0,
      "performance_annualized": 0.0,
      "total_stocks": 20
    },
    {
      "year": "2025",
      "month": "December",
      "day": "07",
      "file": "2025/December/07.tsv",
      "date": "2025-12-07",
      "performance_90_day": 0.0,
      "performance_annualized": 0.0,
      "total_stocks": 20
    },
    {
      "year": "2025",
      "month": "December",
      "day": "08",
      "file": "2025/December/08.tsv",
      "date": "2025-12-08",
      "performance_90_day": 0.0,
      "performance_annualized": 0.0,
      "total_stocks": 20
    },
    {
      "year": "2025",
      "month": "December",
      "day": "11",
      "file": "2025/December/11.tsv",
      "date": "2025-12-11",
      "performance_90_day": 0.0,
      "performance_annualized": 0.0,
      "total_stocks": 20
    },
    {
      "year": "2025",
      "month": "December",
      "day": "12",
      "file": "2025/December/12.tsv",
      "date": "2025-12-12",
      "performance_90_day": 0.0,
      "performance_annualized": 0.0,
      "total_stocks": 20
    },
    {
      "year": "2025",
      "month": "December",
      "day": "14",
      "file": "2025/December/14.tsv",
      "date": "2025-12-14",
      "performance_90_day": 0.0,
      "performance_annualized": 0.0,
      "total_stocks": 20
    },
    {
      "year": "2025",
      "month": "December",
      "day": "15",
      "file": "2025/December/15.tsv",
      "date": "2025-12-15",
      "performance_90_day": 0.0,
      "performance_annualized": 0.0,
      "total_stocks": 20
    },
    {
      "year": "2025",
      "month": "December",
      "day": "16",
      "file": "2025/December/16.tsv",
      "date": "2025-12-16",
      "performance_90_day": 43.82324705039506,
      "performance_annualized": 337.0418789958587,
      "total_stocks": 20
    },
    {
      "year": "2025",
      "month": "December",
      "day": "17",
      "file": "2025/December/17.tsv",
      "date": "2025-12-17",
      "performance_90_day": 19.473770426893783,
      "performance_annualized": 105.87226618024532,
      "total_stocks": 20
    },
    {
      "year": "2025",
      "month": "December",
      "day": "18",
      "file": "2025/December/18.tsv",
      "date": "2025-12-18",
      "performance_90_day": 4.11192036210924,
      "performance_annualized": 17.76674965348455,
      "total_stocks": 20
    },
    {
      "year": "2025",
      "month": "December",
      "day": "19",
      "file": "2025/December/19.tsv",
      "date": "2025-12-19",
      "performance_90_day": 4.712278814471002,
      "performance_annualized": 20.54715679801873,
      "total_stocks": 20
    },
    {
      "year": "2025",
      "month": "December",
      "day": "20",
      "file": "2025/December/20.tsv",
      "date": "2025-12-20",
      "performance_90_day": 6.75044673704731,
      "performance_annualized": 30.35680391653146,
      "total_stocks": 20
    },
    {
      "year": "2025",
      "month": "December",
      "day": "21",
      "file": "2025/December/21.tsv",
      "date": "2025-12-21",
      "performance_90_day": 6.75044673704731,
      "performance_annualized": 30.74567785753464,
      "total_stocks": 20
    },
    {
      "year": "2025",
      "month": "December",
      "day": "22",
      "file": "2025/December/22.tsv",
      "date": "2025-12-22",
      "performance_90_day": 0.7974819659155802,
      "performance_annualized": 3.3518238049135007,
      "total_stocks": 20
    },
    {
      "year": "2025",
      "month": "December",
      "day": "23",
      "file": "2025/December/23.tsv",
      "date": "2025-12-23",
      "performance_90_day": -1.582973883257817,
      "performance_annualized": -6.270410525687231,
      "total_stocks": 20
    },
    {
      "year": "2025",
      "month": "December",
      "day": "24",
      "file": "2025/December/24.tsv",
      "date": "2025-12-24",
      "performance_90_day": -1.061895879817972,
      "performance_annualized": -4.240057076906146,
      "total_stocks": 20
    },
    {
      "year": "2025",
      "month": "December",
      "day": "25",
      "file": "2025/December/25.tsv",
      "date": "2025-12-25",
      "performance_90_day": 1.3688406543279328,
      "performance_annualized": 5.67258857930697,
      "total_stocks": 20
    },
    {
      "year": "2025",
      "month": "December",
      "day": "26",
      "file": "2025/December/26.tsv",
      "date": "2025-12-26",
      "performance_90_day": 22.82931106124314,
      "performance_annualized": 130.36545183485262,
      "total_stocks": 20
    },
    {
      "year": "2025",
      "month": "December",
      "day": "27",
      "file": "2025/December/27.tsv",
      "date": "2025-12-27",
      "performance_90_day": 19.360300209338657,
      "performance_annualized": 105.07990335102456,
      "total_stocks": 20
    },
    {
      "year": "2025",
      "month": "December",
      "day": "28",
      "file": "2025/December/28.tsv",
      "date": "2025-12-28",
      "performance_90_day": 24.52458625093157,
      "performance_annualized": 145.99174830137582,
      "total_stocks": 20
    },
    {
      "year": "2025",
      "month": "December",
      "day": "29",
      "file": "2025/December/29.tsv",
      "date": "2025-12-29",
      "performance_90_day": 15.768836735597096,
      "performance_annualized": 83.62912290933625,
      "total_stocks": 20
    },
    {
      "year": "2025",
      "month": "December",
      "day": "30",
      "file": "2025/December/30.tsv",
      "date": "2025-12-30",
      "performance_90_day": 7.875649604433758,
      "performance_annualized": 36.02358879045966,
      "total_stocks": 20
    },
    {
      "year": "2025",
      "month": "December",
      "day": "31",
      "file": "2025/December/31.tsv",
      "date": "2025-12-31",
      "performance_90_day": 12.684428977325997,
      "performance_annualized": 62.36074211994993,
      "total_stocks": 20
    },
    {
      "year": "2026",
      "month": "January",
      "day": "01",
      "file": "2026/January/01.tsv",
      "date": "2026-01-01",
      "performance_90_day": 20.649435908781825,
      "performance_annualized": 114.2184265928686,
      "total_stocks": 20
    },
    {
      "year": "2026",
      "month": "January",
      "day": "02",
      "file": "2026/January/02.tsv",
      "date": "2026-01-02",
      "performance_90_day": 7.681551182809119,
      "performance_annualized": 35.03306379644646,
      "total_stocks": 20
    },
    {
      "year": "2026",
      "month": "January",
      "day": "03",
      "file": "2026/January/03.tsv",
      "date": "2026-01-03",
      "performance_90_day": 15.177513701359649,
      "performance_annualized": 78.5866130742834,
      "total_stocks": 20
    },
    {
      "year": "2026",
      "month": "January",
      "day": "04",
      "file": "2026/January/04.tsv",
      "date": "2026-01-04",
      "performance_90_day": 15.182157381007272,
      "performance_annualized": 79.7974359111882,
      "total_stocks": 20
    },
    {
      "year": "2026",
      "month": "January",
      "day": "05",
      "file": "2026/January/05.tsv",
      "date": "2026-01-05",
      "performance_90_day": 11.370460997668456,
      "performance_annualized": 57.16413076135745,
      "total_stocks": 20
    },
    {
      "year": "2026",
      "month": "January",
      "day": "06",
      "file": "2026/January/06.tsv",
      "date": "2026-01-06",
      "performance_90_day": 12.471066504033615,
      "performance_annualized": 61.11672823454337,
      "total_stocks": 20
    },
    {
      "year": "2026",
      "month": "January",
      "day": "07",
      "file": "2026/January/07.tsv",
      "date": "2026-01-07",
      "performance_90_day": 10.97910209100994,
      "performance_annualized": 52.61734609321216,
      "total_stocks": 20
    },
    {
      "year": "2026",
      "month": "January",
      "day": "08",
      "file": "2026/January/08.tsv",
      "date": "2026-01-08",
      "performance_90_day": 15.730569793908623,
      "performance_annualized": 80.92288487090016,
      "total_stocks": 20
    },
    {
      "year": "2026",
      "month": "January",
      "day": "09",
      "file": "2026/January/09.tsv",
      "date": "2026-01-09",
      "performance_90_day": 12.121497083125398,
      "performance_annualized": 59.09409860682906,
      "total_stocks": 20
    },
    {
      "year": "2026",
      "month": "January",
      "day": "10",
      "file": "2026/January/10.tsv",
      "date": "2026-01-10",
      "performance_90_day": 8.179093772669281,
      "performance_annualized": 37.58308734909232,
      "total_stocks": 20
    },
    {
      "year": "2026",
      "month": "January",
      "day": "11",
      "file": "2026/January/11.tsv",
      "date": "2026-01-11",
      "performance_90_day": 10.18838408880451,
      "performance_annualized": 48.90954643683827,
      "total_stocks": 20
    },
    {
      "year": "2026",
      "month": "January",
      "day": "12",
      "file": "2026/January/12.tsv",
      "date": "2026-01-12",
      "performance_90_day": 11.24169377116001,
      "performance_annualized": 55.609747730872506,
      "total_stocks": 20
    },
    {
      "year": "2026",
      "month": "January",
      "day": "13",
      "file": "2026/January/13.tsv",
      "date": "2026-01-13",
      "performance_90_day": 8.956078798451745,
      "performance_annualized": 41.637698933820545,
      "total_stocks": 20
    },
    {
      "year": "2026",
      "month": "January",
      "day": "14",
      "file": "2026/January/14.tsv",
      "date": "2026-01-14",
      "performance_90_day": -2.22392636383557,
      "performance_annualized": -8.723157479533972,
      "total_stocks": 20
    },
    {
      "year": "2026",
      "month": "January",
      "day": "15",
      "file": "2026/January/15.tsv",
      "date": "2026-01-15",
      "performance_90_day": 0.3002027495469168,
      "performance_annualized": 1.2239271873127011,
      "total_stocks": 20
    },
    {
      "year": "2026",
      "month": "January",
      "day": "16",
      "file": "2026/January/16.tsv",
      "date": "2026-01-16",
      "performance_90_day": 63.82805363113967,
      "performance_annualized": 641.4110748179266,
      "total_stocks": 20
    },
    {
      "year": "2026",
      "month": "January",
      "day": "17",
      "file": "2026/January/17.tsv",
      "date": "2026-01-17",
      "performance_90_day": 13.29568763174256,
      "performance_annualized": 65.96479190772354,
      "total_stocks": 20
    },
    {
      "year": "2026",
      "month": "January",
      "day": "18",
      "file": "2026/January/18.tsv",
      "date": "2026-01-18",
      "performance_90_day": 8.648721406731557,
      "performance_annualized": 40.553806338138074,
      "total_stocks": 20
    },
    {
      "year": "2026",
      "month": "January",
      "day": "19",
      "file": "2026/January/19.tsv",
      "date": "2026-01-19",
      "performance_90_day": 8.515464201075044,
      "performance_annualized": 40.3816817165648,
      "total_stocks": 20
    },
    {
      "year": "2026",
      "month": "January",
      "day": "20",
      "file": "2026/January/20.tsv",
      "date": "2026-01-20",
      "performance_90_day": 10.370294253326756,
      "performance_annualized": 49.24799767740167,
      "total_stocks": 20
    },
    {
      "year": "2026",
      "month": "January",
      "day": "21",
      "file": "2026/January/21.tsv",
      "date": "2026-01-21",
      "performance_90_day": -0.5243140793763587,
      "performance_annualized": -2.1108423351852035,
      "total_stocks": 20
    },
    {
      "year": "2026",
      "month": "January",
      "day": "22",
      "file": "2026/January/22.tsv",
      "date": "2026-01-22",
      "performance_90_day": 17.77368559018708,
      "performance_annualized": 94.23949765097343,
      "total_stocks": 20
    },
    {
      "year": "2026",
      "month": "January",
      "day": "23",
      "file": "2026/January/23.tsv",
      "date": "2026-01-23",
      "performance_90_day": 30.436953658553488,
      "performance_annualized": 193.99117488683163,
      "total_stocks": 20
    },
    {
      "year": "2026",
      "month": "January",
      "day": "24",
      "file": "2026/January/24.tsv",
      "date": "2026-01-24",
      "performance_90_day": 14.765336329547353,
      "performance_annualized": 74.87667791233581,
      "total_stocks": 20
    },
    {
      "year": "2026",
      "month": "January",
      "day": "25",
      "file": "2026/January/25.tsv",
      "date": "2026-01-25",
      "performance_90_day": 12.432493392015118,
      "performance_annualized": 61.754618150936565,
      "total_stocks": 20
    },
    {
      "year": "2026",
      "month": "January",
      "day": "26",
      "file": "2026/January/26.tsv",
      "date": "2026-01-26",
      "performance_90_day": 12.198890367128834,
      "performance_annualized": 61.243023893894424,
      "total_stocks": 20
    },
    {
      "year": "2026",
      "month": "January",
      "day": "28",
      "file": "2026/January/28.tsv",
      "date": "2026-01-28",
      "performance_90_day": 1.3359029036658343,
      "performance_annualized": 5.533310193360341,
      "total_stocks": 20
    },
    {
      "year": "2026",
      "month": "January",
      "day": "29",
      "file": "2026/January/29.tsv",
      "date": "2026-01-29",
      "performance_90_day": 11.742279083150198,
      "performance_annualized": 56.92162206933513,
      "total_stocks": 20
    },
    {
      "year": "2026",
      "month": "January",
      "day": "30",
      "file": "2026/January/30.tsv",
      "date": "2026-01-30",
      "performance_90_day": 9.99914896185403,
      "performance_annualized": 47.22164898985935,
      "total_stocks": 20
    },
    {
      "year": "2026",
      "month": "January",
      "day": "31",
      "file": "2026/January/31.tsv",
      "date": "2026-01-31",
      "performance_90_day": 12.0771191527364,
      "performance_annualized": 58.83870085010299,
      "total_stocks": 20
    },
    {
      "year": "2026",
      "month": "February",
      "day": "01",
      "file": "2026/February/01.tsv",
      "date": "2026-02-01",
      "performance_90_day": 5.449803186631527,
      "performance_annualized": 24.330677671318092,
      "total_stocks": 20
    },
    {
      "year": "2026",
      "month": "February",
      "day": "02",
      "file": "2026/February/02.tsv",
      "date": "2026-02-02",
      "performance_90_day": 5.449803186631527,
      "performance_annualized": 24.638741218716163,
      "total_stocks": 20
    },
    {
      "year": "2026",
      "month": "February",
      "day": "04",
      "file": "2026/February/04.tsv",
      "date": "2026-02-04",
      "performance_90_day": 17.51474810930199,
      "performance_annualized": 92.51218262112808,
      "total_stocks": 20
    },
    {
      "year": "2026",
      "month": "February",
      "day": "05",
      "file": "2026/February/05.tsv",
      "date": "2026-02-05",
      "performance_90_day": 26.337770905696676,
      "performance_annualized": 158.25908645004637,
      "total_stocks": 20
    },
    {
      "year": "2026",
      "month": "February",
      "day": "06",
      "file": "2026/February/06.tsv",
      "date": "2026-02-06",
      "performance_90_day": 8.708356837409793,
      "performance_annualized": 40.335343760919585,
      "total_stocks": 20
    },
    {
      "year": "2026",
      "month": "February",
      "day": "07",
      "file": "2026/February/07.tsv",
      "date": "2026-02-07",
      "performance_90_day": 5.640886994439758,
      "performance_annualized": 24.94484953219511,
      "total_stocks": 20
    },
    {
      "year": "2026",
      "month": "February",
      "day": "08",
      "file": "2026/February/08.tsv",
      "date": "2026-02-08",
      "performance_90_day": 32.95080635332114,
      "performance_annualized": 221.82473886429185,
      "total_stocks": 20
    },
    {
      "year": "2026",
      "month": "February",
      "day": "09",
      "file": "2026/February/09.tsv",
      "date": "2026-02-09",
      "performance_90_day": 25.134018182461276,
      "performance_annualized": 153.60814487320286,
      "total_stocks": 20
    },
    {
      "year": "2026",
      "month": "February",
      "day": "10",
      "file": "2026/February/10.tsv",
      "date": "2026-02-10",
      "performance_90_day": 36.709814118906955,
      "performance_annualized": 255.7299406968668,
      "total_stocks": 20
    },
    {
      "year": "2026",
      "month": "February",
      "day": "11",
      "file": "2026/February/11.tsv",
      "date": "2026-02-11",
      "performance_90_day": 231.15752141878616,
      "performance_annualized": 12796.558921804111,
      "total_stocks": 20
    },
    {
      "year": "2026",
      "month": "February",
      "day": "12",
      "file": "2026/February/12.tsv",
      "date": "2026-02-12",
      "performance_90_day": 40.815937033167266,
      "performance_annualized": 301.1239500696361,
      "total_stocks": 20
    },
    {
      "year": "2026",
      "month": "February",
      "day": "13",
      "file": "2026/February/13.tsv",
      "date": "2026-02-13",
      "performance_90_day": 16.532620567320652,
      "performance_annualized": 86.06562948453377,
      "total_stocks": 20
    },
    {
      "year": "2026",
      "month": "February",
      "day": "14",
      "file": "2026/February/14.tsv",
      "date": "2026-02-14",
      "performance_90_day": 14.954177293754848,
      "performance_annualized": 76.04741048950743,
      "total_stocks": 20
    },
    {
      "year": "2026",
      "month": "February",
      "day": "15",
      "file": "2026/February/15.tsv",
      "date": "2026-02-15",
      "performance_90_day": 14.954177293754848,
      "performance_annualized": 77.16973066488141,
      "total_stocks": 20
    },
    {
      "year": "2026",
      "month": "February",
      "day": "16",
      "file": "2026/February/16.tsv",
      "date": "2026-02-16",
      "performance_90_day": 15.229493573651013,
      "performance_annualized": 80.10432419734687,
      "total_stocks": 20
    },
    {
      "year": "2026",
      "month": "February",
      "day": "17",
      "file": "2026/February/17.tsv",
      "date": "2026-02-17",
      "performance_90_day": 16.649601585574707,
      "performance_annualized": 86.82481579367266,
      "total_stocks": 20
    },
    {
      "year": "2026",
      "month": "February",
      "day": "18",
      "file": "2026/February/18.tsv",
      "date": "2026-02-18",
      "performance_90_day": 9.095626066995136,
      "performance_annualized": 42.37534313912932,
      "total_stocks": 20
    },
    {
      "year": "2026",
      "month": "February",
      "day": "19",
      "file": "2026/February/19.tsv",
      "date": "2026-02-19",
      "performance_90_day": 11.948852607944833,
      "performance_annualized": 58.10225575914656,
      "total_stocks": 20
    },
    {
      "year": "2026",
      "month": "February",
      "day": "20",
      "file": "2026/February/20.tsv",
      "date": "2026-02-20",
      "performance_90_day": 1.3829499205679945,
      "performance_annualized": 5.732292444077203,
      "total_stocks": 20
    },
    {
      "year": "2026",
      "month": "February",
      "day": "21",
      "file": "2026/February/21.tsv",
      "date": "2026-02-21",
      "performance_90_day": 35.57734515026249,
      "performance_annualized": 243.9215719969977,
      "total_stocks": 20
    },
    {
      "year": "2026",
      "month": "February",
      "day": "22",
      "file": "2026/February/22.tsv",
      "date": "2026-02-22",
      "performance_90_day": 8.849717929169927,
      "performance_annualized": 41.62397807479141,
      "total_stocks": 20
    },
    {
      "year": "2026",
      "month": "February",
      "day": "23",
      "file": "2026/February/23.tsv",
      "date": "2026-02-23",
      "performance_90_day": 8.849717929169927,
      "performance_annualized": 42.185153974937805,
      "total_stocks": 20
    },
    {
      "year": "2026",
      "month": "February",
      "day": "24",
      "file": "2026/February/24.tsv",
      "date": "2026-02-24",
      "performance_90_day": 17.86714619674836,
      "performance_annualized": 99.40063488018616,
      "total_stocks": 20
    },
    {
      "year": "2026",
      "month": "February",
      "day": "25",
      "file": "2026/February/25.tsv",
      "date": "2026-02-25",
      "performance_90_day": 17.504174105088094,
      "performance_annualized": 92.4418926635665,
      "total_stocks": 20
    },
    {
      "year": "2026",
      "month": "February",
      "day": "26",
      "file": "2026/February/26.tsv",
      "date": "2026-02-26",
      "performance_90_day": 12.755453307707906,
      "performance_annualized": 62.77645219065011,
      "total_stocks": 20
    },
    {
      "year": "2026",
      "month": "February",
      "day": "27",
      "file": "2026/February/27.tsv",
      "date": "2026-02-27",
      "performance_90_day": 7.1688296450569755,
      "performance_annualized": 32.442675960506826,
      "total_stocks": 20
    },
    {
      "year": "2026",
      "month": "March",
      "day": "02",
      "file": "2026/March/02.tsv",
      "date": "2026-03-02",
      "performance_90_day": -3.426242303299966,
      "performance_annualized": -13.471975710334938,
      "total_stocks": 20
    },
    {
      "year": "2026",
      "month": "March",
      "day": "04",
      "file": "2026/March/04.tsv",
      "date": "2026-03-04",
      "performance_90_day": -8.337064651478713,
      "performance_annualized": -29.762397527581346,
      "total_stocks": 20
    },
    {
      "year": "2026",
      "month": "March",
      "day": "05",
      "file": "2026/March/05.tsv",
      "date": "2026-03-05",
      "performance_90_day": -1.4075544295358675,
      "performance_annualized": -5.590556780639111,
      "total_stocks": 20
    },
    {
      "year": "2026",
      "month": "March",
      "day": "06",
      "file": "2026/March/06.tsv",
      "date": "2026-03-06",
      "performance_90_day": 2.1923710021508,
      "performance_annualized": 9.200169640684395,
      "total_stocks": 20
    },
    {
      "year": "2026",
      "month": "March",
      "day": "07",
      "file": "2026/March/07.tsv",
      "date": "2026-03-07",
      "performance_90_day": 1.4612321794819634,
      "performance_annualized": 6.064008540274868,
      "total_stocks": 20
    },
    {
      "year": "2026",
      "month": "March",
      "day": "08",
      "file": "2026/March/08.tsv",
      "date": "2026-03-08",
      "performance_90_day": 3.984646735540312,
      "performance_annualized": 17.392550393235908,
      "total_stocks": 20
    },
    {
      "year": "2026",
      "month": "March",
      "day": "09",
      "file": "2026/March/09.tsv",
      "date": "2026-03-09",
      "performance_90_day": 3.984646735540312,
      "performance_annualized": 17.606657664459526,
      "total_stocks": 20
    },
    {
      "year": "2026",
      "month": "March",
      "day": "10",
      "file": "2026/March/10.tsv",
      "date": "2026-03-10",
      "performance_90_day": 4.030192166584761,
      "performance_annualized": 17.392017898130984,
      "total_stocks": 20
    },
    {
      "year": "2026",
      "month": "March",
      "day": "11",
      "file": "2026/March/11.tsv",
      "date": "2026-03-11",
      "performance_90_day": 20.353209724708194,
      "performance_annualized": 112.0918951256621,
      "total_stocks": 20
    },
    {
      "year": "2026",
      "month": "March",
      "day": "12",
      "file": "2026/March/12.tsv",
      "date": "2026-03-12",
      "performance_90_day": 11.0668416934874,
      "performance_annualized": 53.10761130413886,
      "total_stocks": 20
    },
    {
      "year": "2026",
      "month": "March",
      "day": "13",
      "file": "2026/March/13.tsv",
      "date": "2026-03-13",
      "performance_90_day": 10.864939927962135,
      "performance_annualized": 51.98121095839006,
      "total_stocks": 20
    },
    {
      "year": "2026",
      "month": "March",
      "day": "14",
      "file": "2026/March/14.tsv",
      "date": "2026-03-14",
      "performance_90_day": 7.758439124634028,
      "performance_annualized": 35.42478667456772,
      "total_stocks": 20
    },
    {
      "year": "2026",
      "month": "March",
      "day": "15",
      "file": "2026/March/15.tsv",
      "date": "2026-03-15",
      "performance_90_day": 5.592892787947394,
      "performance_annualized": 25.024511261404815,
      "total_stocks": 20
    },
    {
      "year": "2026",
      "month": "March",
      "day": "16",
      "file": "2026/March/16.tsv",
      "date": "2026-03-16",
      "performance_90_day": 2.780483319056714,
      "performance_annualized": 12.056225122895592,
      "total_stocks": 20
    },
    {
      "year": "2026",
      "month": "March",
      "day": "17",
      "file": "2026/March/17.tsv",
      "date": "2026-03-17",
      "performance_90_day": 6.286842112814502,
      "performance_annualized": 29.171963791035903,
      "total_stocks": 20
    },
    {
      "year": "2026",
      "month": "March",
      "day": "18",
      "file": "2026/March/18.tsv",
      "date": "2026-03-18",
      "performance_90_day": 6.338500383296088,
      "performance_annualized": 29.82465286138687,
      "total_stocks": 20
    },
    {
      "year": "2026",
      "month": "March",
      "day": "19",
      "file": "2026/March/19.tsv",
      "date": "2026-03-19",
      "performance_90_day": 7.1422785915946845,
      "performance_annualized": 34.50661900985579,
      "total_stocks": 20
    },
    {
      "year": "2026",
      "month": "March",
      "day": "20",
      "file": "2026/March/20.tsv",
      "date": "2026-03-20",
      "performance_90_day": 12.904616139130628,
      "performance_annualized": 69.51251236403915,
      "total_stocks": 20
    },
    {
      "year": "2026",
      "month": "March",
      "day": "21",
      "file": "2026/March/21.tsv",
      "date": "2026-03-21",
      "performance_90_day": 11.415726252420214,
      "performance_annualized": 60.913640851743686,
      "total_stocks": 20
    },
    {
      "year": "2026",
      "month": "March",
      "day": "22",
      "file": "2026/March/22.tsv",
      "date": "2026-03-22",
      "performance_90_day": 14.52656865160484,
      "performance_annualized": 82.97183220014168,
      "total_stocks": 20
    },
    {
      "year": "2026",
      "month": "March",
      "day": "23",
      "file": "2026/March/23.tsv",
      "date": "2026-03-23",
      "performance_90_day": 12.952325751652287,
      "performance_annualized": 73.18810883906627,
      "total_stocks": 20
    },
    {
      "year": "2026",
      "month": "March",
      "day": "24",
      "file": "2026/March/24.tsv",
      "date": "2026-03-24",
      "performance_90_day": 9.155444391919366,
      "performance_annualized": 49.17671481457169,
      "total_stocks": 20
    },
    {
      "year": "2026",
      "month": "March",
      "day": "25",
      "file": "2026/March/25.tsv",
      "date": "2026-03-25",
      "performance_90_day": 3.785933735358195,
      "performance_annualized": 18.744912723015304,
      "total_stocks": 20
    },
    {
      "year": "2026",
      "month": "March",
      "day": "27",
      "file": "2026/March/27.tsv",
      "date": "2026-03-27",
      "performance_90_day": 7.986081988922754,
      "performance_annualized": 43.97275021439668,
      "total_stocks": 20
    },
    {
      "year": "2026",
      "month": "March",
      "day": "28",
      "file": "2026/March/28.tsv",
      "date": "2026-03-28",
      "performance_90_day": 9.10731547196526,
      "performance_annualized": 52.02769548419146,
      "total_stocks": 20
    },
    {
      "year": "2026",
      "month": "March",
      "day": "29",
      "file": "2026/March/29.tsv",
      "date": "2026-03-29",
      "performance_90_day": 9.196078357630462,
      "performance_annualized": 53.48583177873465,
      "total_stocks": 20
    },
    {
      "year": "2026",
      "month": "March",
      "day": "30",
      "file": "2026/March/30.tsv",
      "date": "2026-03-30",
      "performance_90_day": 8.715566872022443,
      "performance_annualized": 51.05292402760777,
      "total_stocks": 20
    },
    {
      "year": "2026",
      "month": "March",
      "day": "31",
      "file": "2026/March/31.tsv",
      "date": "2026-03-31",
      "performance_90_day": 4.422838998647087,
      "performance_annualized": 24.17719637219933,
      "total_stocks": 20
    },
    {
      "year": "2026",
      "month": "April",
      "day": "01",
      "file": "2026/April/01.tsv",
      "date": "2026-04-01",
      "performance_90_day": 3.419186485733875,
      "performance_annualized": 18.59605719106503,
      "total_stocks": 20
    },
    {
      "year": "2026",
      "month": "April",
      "day": "02",
      "file": "2026/April/02.tsv",
      "date": "2026-04-02",
      "performance_90_day": 26.955810395463335,
      "performance_annualized": 241.3711689984673,
      "total_stocks": 20
    },
    {
      "year": "2026",
      "month": "April",
      "day": "03",
      "file": "2026/April/03.tsv",
      "date": "2026-04-03",
      "performance_90_day": 12.20269008757924,
      "performance_annualized": 82.35174189353036,
      "total_stocks": 20
    },
    {
      "year": "2026",
      "month": "April",
      "day": "04",
      "file": "2026/April/04.tsv",
      "date": "2026-04-04",
      "performance_90_day": 27.686051986003605,
      "performance_annualized": 264.64317753069764,
      "total_stocks": 20
    },
    {
      "year": "2026",
      "month": "April",
      "day": "05",
      "file": "2026/April/05.tsv",
      "date": "2026-04-05",
      "performance_90_day": 30.93065901948282,
      "performance_annualized": 325.27218426267683,
      "total_stocks": 20
    },
    {
      "year": "2026",
      "month": "April",
      "day": "06",
      "file": "2026/April/06.tsv",
      "date": "2026-04-06",
      "performance_90_day": 30.930659019482817,
      "performance_annualized": 334.5603189363375,
      "total_stocks": 20
    },
    {
      "year": "2026",
      "month": "April",
      "day": "07",
      "file": "2026/April/07.tsv",
      "date": "2026-04-07",
      "performance_90_day": 30.76500372156532,
      "performance_annualized": 341.2398415167452,
      "total_stocks": 20
    },
    {
      "year": "2026",
      "month": "April",
      "day": "08",
      "file": "2026/April/08.tsv",
      "date": "2026-04-08",
      "performance_90_day": 5.352776554228643,
      "performance_annualized": 34.045741209736406,
      "total_stocks": 20
    },
    {
      "year": "2026",
      "month": "April",
      "day": "09",
      "file": "2026/April/09.tsv",
      "date": "2026-04-09",
      "performance_90_day": 5.773362877429683,
      "performance_annualized": 37.75785615224163,
      "total_stocks": 20
    },
    {
      "year": "2026",
      "month": "April",
      "day": "10",
      "file": "2026/April/10.tsv",
      "date": "2026-04-10",
      "performance_90_day": 15.099942572756428,
      "performance_annualized": 125.99051058492336,
      "total_stocks": 20
    },
    {
      "year": "2026",
      "month": "April",
      "day": "11",
      "file": "2026/April/11.tsv",
      "date": "2026-04-11",
      "performance_90_day": 15.559271111703186,
      "performance_annualized": 134.41810160495424,
      "total_stocks": 20
    },
    {
      "year": "2026",
      "month": "April",
      "day": "12",
      "file": "2026/April/12.tsv",
      "date": "2026-04-12",
      "performance_90_day": 7.114605843710899,
      "performance_annualized": 50.912485550533894,
      "total_stocks": 20
    },
    {
      "year": "2026",
      "month": "April",
      "day": "13",
      "file": "2026/April/13.tsv",
      "date": "2026-04-13",
      "performance_90_day": 18.95099612429852,
      "performance_annualized": 187.60948665771403,
      "total_stocks": 20
    },
    {
      "year": "2026",
      "month": "April",
      "day": "14",
      "file": "2026/April/14.tsv",
      "date": "2026-04-14",
      "performance_90_day": 4.784113484123149,
      "performance_annualized": 33.54958859706257,
      "total_stocks": 20
    },
    {
      "year": "2026",
      "month": "April",
      "day": "15",
      "file": "2026/April/15.tsv",
      "date": "2026-04-15",
      "performance_90_day": 9.65086171559363,
      "performance_annualized": 78.63741658146826,
      "total_stocks": 20
    },
    {
      "year": "2026",
      "month": "April",
      "day": "16",
      "file": "2026/April/16.tsv",
      "date": "2026-04-16",
      "performance_90_day": 8.364132581302767,
      "performance_annualized": 67.31812519066509,
      "total_stocks": 20
    },
    {
      "year": "2026",
      "month": "April",
      "day": "17",
      "file": "2026/April/17.tsv",
      "date": "2026-04-17",
      "performance_90_day": 3.2794989889654333,
      "performance_annualized": 23.425419343834864,
      "total_stocks": 20
    },
    {
      "year": "2026",
      "month": "April",
      "day": "18",
      "file": "2026/April/18.tsv",
      "date": "2026-04-18",
      "performance_90_day": 2.5402811384918462,
      "performance_annualized": 18.127063897257862,
      "total_stocks": 20
    },
    {
      "year": "2026",
      "month": "April",
      "day": "19",
      "file": "2026/April/19.tsv",
      "date": "2026-04-19",
      "performance_90_day": 1.600381810895211,
      "performance_annualized": 11.3369484061834,
      "total_stocks": 20
    },
    {
      "year": "2026",
      "month": "April",
      "day": "20",
      "file": "2026/April/20.tsv",
      "date": "2026-04-20",
      "performance_90_day": 1.140323611385305,
      "performance_annualized": 8.127491533896158,
      "total_stocks": 20
    },
    {
      "year": "2026",
      "month": "April",
      "day": "21",
      "file": "2026/April/21.tsv",
      "date": "2026-04-21",
      "performance_90_day": 1.5121393410138662,
      "performance_annualized": 11.117521498606076,
      "total_stocks": 20
    },
    {
      "year": "2026",
      "month": "April",
      "day": "22",
      "file": "2026/April/22.tsv",
      "date": "2026-04-22",
      "performance_90_day": 2.2130812788736733,
      "performance_annualized": 16.972339754599464,
      "total_stocks": 20
    },
    {
      "year": "2026",
      "month": "April",
      "day": "23",
      "file": "2026/April/23.tsv",
      "date": "2026-04-23",
      "performance_90_day": 6.516468052164704,
      "performance_annualized": 58.59131951234622,
      "total_stocks": 20
    },
    {
      "year": "2026",
      "month": "April",
      "day": "24",
      "file": "2026/April/24.tsv",
      "date": "2026-04-24",
      "performance_90_day": 5.002699975381104,
      "performance_annualized": 43.889799413889065,
      "total_stocks": 20
    },
    {
      "year": "2026",
      "month": "April",
      "day": "26",
      "file": "2026/April/26.tsv",
      "date": "2026-04-26",
      "performance_90_day": 5.240904792334019,
      "performance_annualized": 48.73132760908614,
      "total_stocks": 20
    },
    {
      "year": "2026",
      "month": "April",
      "day": "27",
      "file": "2026/April/27.tsv",
      "date": "2026-04-27",
      "performance_90_day": 5.780578733460339,
      "performance_annualized": 56.23864337028874,
      "total_stocks": 20
    },
    {
      "year": "2026",
      "month": "April",
      "day": "28",
      "file": "2026/April/28.tsv",
      "date": "2026-04-28",
      "performance_90_day": 0.4416220954113072,
      "performance_annualized": 3.641337613298523,
      "total_stocks": 20
    },
    {
      "year": "2026",
      "month": "April",
      "day": "29",
      "file": "2026/April/29.tsv",
      "date": "2026-04-29",
      "performance_90_day": 10.28966316204293,
      "performance_annualized": 125.46921916306144,
      "total_stocks": 20
    },
    {
      "year": "2026",
      "month": "April",
      "day": "30",
      "file": "2026/April/30.tsv",
      "date": "2026-04-30",
      "performance_90_day": 7.42316465552315,
      "performance_annualized": 83.71799984445194,
      "total_stocks": 20
    },
    {
      "year": "2026",
      "month": "May",
      "day": "01",
      "file": "2026/May/01.tsv",
      "date": "2026-05-01",
      "performance_90_day": 6.434599625355797,
      "performance_annualized": 71.9982006892342,
      "total_stocks": 20
    },
    {
      "year": "2026",
      "month": "May",
      "day": "03",
      "file": "2026/May/03.tsv",
      "date": "2026-05-03",
      "performance_90_day": 0.05912334836942266,
      "performance_annualized": 0.5411696041154546,
      "total_stocks": 20
    },
    {
      "year": "2026",
      "month": "May",
      "day": "04",
      "file": "2026/May/04.tsv",
      "date": "2026-05-04",
      "performance_90_day": 0.05912334836942266,
      "performance_annualized": 0.5550841897777437,
      "total_stocks": 20
    },
    {
      "year": "2026",
      "month": "May",
      "day": "05",
      "file": "2026/May/05.tsv",
      "date": "2026-05-05",
      "performance_90_day": -0.943274212316818,
      "performance_annualized": -8.707025481208596,
      "total_stocks": 20
    },
    {
      "year": "2026",
      "month": "May",
      "day": "06",
      "file": "2026/May/06.tsv",
      "date": "2026-05-06",
      "performance_90_day": -5.1157853773157616,
      "performance_annualized": -40.45195972023761,
      "total_stocks": 20
    },
    {
      "year": "2026",
      "month": "May",
      "day": "07",
      "file": "2026/May/07.tsv",
      "date": "2026-05-07",
      "performance_90_day": -1.8168128299989816,
      "performance_annualized": -16.974785596370413,
      "total_stocks": 20
    },
    {
      "year": "2026",
      "month": "May",
      "day": "08",
      "file": "2026/May/08.tsv",
      "date": "2026-05-08",
      "performance_90_day": 2.3496622178547595,
      "performance_annualized": 27.426258538702776,
      "total_stocks": 20
    },
    {
      "year": "2026",
      "month": "May",
      "day": "09",
      "file": "2026/May/09.tsv",
      "date": "2026-05-09",
      "performance_90_day": 3.245252081699872,
      "performance_annualized": 40.92935703581404,
      "total_stocks": 20
    },
    {
      "year": "2026",
      "month": "May",
      "day": "10",
      "file": "2026/May/10.tsv",
      "date": "2026-05-10",
      "performance_90_day": 3.245252081699872,
      "performance_annualized": 42.402189431011394,
      "total_stocks": 20
    },
    {
      "year": "2026",
      "month": "May",
      "day": "11",
      "file": "2026/May/11.tsv",
      "date": "2026-05-11",
      "performance_90_day": 4.2511653751199825,
      "performance_annualized": 60.833581554577435,
      "total_stocks": 20
    },
    {
      "year": "2026",
      "month": "May",
      "day": "12",
      "file": "2026/May/12.tsv",
      "date": "2026-05-12",
      "performance_90_day": 5.939772784354917,
      "performance_annualized": 97.3567762302776,
      "total_stocks": 20
    },
    {
      "year": "2026",
      "month": "May",
      "day": "13",
      "file": "2026/May/13.tsv",
      "date": "2026-05-13",
      "performance_90_day": 6.411435846525437,
      "performance_annualized": 113.09957957451684,
      "total_stocks": 20
    },
    {
      "year": "2026",
      "month": "May",
      "day": "14",
      "file": "2026/May/14.tsv",
      "date": "2026-05-14",
      "performance_90_day": 5.422126674976015,
      "performance_annualized": 94.4561696008072,
      "total_stocks": 20
    },
    {
      "year": "2026",
      "month": "May",
      "day": "15",
      "file": "2026/May/15.tsv",
      "date": "2026-05-15",
      "performance_90_day": 6.892245395531591,
      "performance_annualized": 138.55737175400793,
      "total_stocks": 20
    },
    {
      "year": "2026",
      "month": "May",
      "day": "16",
      "file": "2026/May/16.tsv",
      "date": "2026-05-16",
      "performance_90_day": 7.815322168342287,
      "performance_annualized": 176.7542751666477,
      "total_stocks": 20
    },
    {
      "year": "2026",
      "month": "May",
      "day": "17",
      "file": "2026/May/17.tsv",
      "date": "2026-05-17",
      "performance_90_day": 7.423015320052867,
      "performance_annualized": 173.43733073551468,
      "total_stocks": 20
    },
    {
      "year": "2026",
      "month": "May",
      "day": "18",
      "file": "2026/May/18.tsv",
      "date": "2026-05-18",
      "performance_90_day": 6.91777447680411,
      "performance_annualized": 165.71690685760117,
      "total_stocks": 20
    },
    {
      "year": "2026",
      "month": "May",
      "day": "19",
      "file": "2026/May/19.tsv",
      "date": "2026-05-19",
      "performance_90_day": 8.907534268198495,
      "performance_annualized": 266.4167372208234,
      "total_stocks": 20
    },
    {
      "year": "2026",
      "month": "May",
      "day": "20",
      "file": "2026/May/20.tsv",
      "date": "2026-05-20",
      "performance_90_day": 6.563122919440401,
      "performance_annualized": 174.41648690670254,
      "total_stocks": 20
    },
    {
      "year": "2026",
      "month": "May",
      "day": "21",
      "file": "2026/May/21.tsv",
      "date": "2026-05-21",
      "performance_90_day": 3.0696135479128706,
      "performance_annualized": 65.1956450454867,
      "total_stocks": 20
    },
    {
      "year": "2026",
      "month": "May",
      "day": "22",
      "file": "2026/May/22.tsv",
      "date": "2026-05-22",
      "performance_90_day": 4.655933756772544,
      "performance_annualized": 120.67337621063469,
      "total_stocks": 20
    },
    {
      "year": "2026",
      "month": "May",
      "day": "23",
      "file": "2026/May/23.tsv",
      "date": "2026-05-23",
      "performance_90_day": -0.554730228689668,
      "performance_annualized": -9.659980822914516,
      "total_stocks": 20
    },
    {
      "year": "2026",
      "month": "May",
      "day": "27",
      "file": "2026/May/27.tsv",
      "date": "2026-05-27",
      "performance_90_day": -2.32827366564812,
      "performance_annualized": -41.59603314746603,
      "total_stocks": 20
    },
    {
      "year": "2026",
      "month": "May",
      "day": "28",
      "file": "2026/May/28.tsv",
      "date": "2026-05-28",
      "performance_90_day": 0.28117621917163244,
      "performance_annualized": 7.076177432794228,
      "total_stocks": 20
    },
    {
      "year": "2026",
      "month": "May",
      "day": "29",
      "file": "2026/May/29.tsv",
      "date": "2026-05-29",
      "performance_90_day": 2.0867016394941484,
      "performance_annualized": 71.39545344857152,
      "total_stocks": 20
    },
    {
      "year": "2026",
      "month": "June",
      "day": "02",
      "file": "2026/June/02.tsv",
      "date": "2026-06-02",
      "performance_90_day": 3.063971485101123,
      "performance_annualized": 201.11234371701676,
      "total_stocks": 20
    },
    {
      "year": "2026",
      "month": "June",
      "day": "03",
      "file": "2026/June/03.tsv",
      "date": "2026-06-03",
      "performance_90_day": 1.4676326523973582,
      "performance_annualized": 80.6309539864655,
      "total_stocks": 20
    },
    {
      "year": "2026",
      "month": "June",
      "day": "04",
      "file": "2026/June/04.tsv",
      "date": "2026-06-04",
      "performance_90_day": 3.657137458066793,
      "performance_annualized": 415.46774670928215,
      "total_stocks": 20
    },
    {
      "year": "2026",
      "month": "June",
      "day": "05",
      "file": "2026/June/05.tsv",
      "date": "2026-06-05",
      "performance_90_day": 4.0078003868848375,
      "performance_annualized": 677.0963994905711,
      "total_stocks": 20
    },
    {
      "year": "2026",
      "month": "June",
      "day": "06",
      "file": "2026/June/06.tsv",
      "date": "2026-06-06",
      "performance_90_day": 3.2403725586699075,
      "performance_annualized": 596.7743474912717,
      "total_stocks": 20
    },
    {
      "year": "2026",
      "month": "June",
      "day": "07",
      "file": "2026/June/07.tsv",
      "date": "2026-06-07",
      "performance_90_day": 3.2403725586699075,
      "performance_annualized": 927.3314509920416,
      "total_stocks": 20
    },
    {
      "year": "2026",
      "month": "June",
      "day": "08",
      "file": "2026/June/08.tsv",
      "date": "2026-06-08",
      "performance_90_day": 3.2403725586699075,
      "performance_annualized": 1739.2392650262093,
      "total_stocks": 20
    },
    {
      "year": "2026",
      "month": "June",
      "day": "09",
      "file": "2026/June/09.tsv",
      "date": "2026-06-09",
      "performance_90_day": 2.4238704371103177,
      "performance_annualized": 1746.477602903653,
      "total_stocks": 20
    },
    {
      "year": "2026",
      "month": "June",
      "day": "10",
      "file": "2026/June/10.tsv",
      "date": "2026-06-10",
      "performance_90_day": 1.8254333256200828,
      "performance_annualized": 2621.139138179161,
      "total_stocks": 20
    },
    {
      "year": "2026",
      "month": "June",
      "day": "11",
      "file": "2026/June/11.tsv",
      "date": "2026-06-11",
      "performance_90_day": 1.4864899353656786,
      "performance_annualized": 21808.202662142965,
      "total_stocks": 20
    },
    {
      "year": "2026",
      "month": "June",
      "day": "12",
      "file": "2026/June/12.tsv",
      "date": "2026-06-12",
      "performance_90_day": 0.0,
      "performance_annualized": 0.0,
      "total_stocks": 20
    },
    {
      "year": "2026",
      "month": "June",
      "day": "13",
      "file": "2026/June/13.tsv",
      "date": "2026-06-13",
      "performance_90_day": 0.0,
      "performance_annualized": 0.0,
      "total_stocks": 20
    },
    {
      "year": "2026",
      "month": "June",
      "day": "14",
      "file": "2026/June/14.tsv",
      "date": "2026-06-14",
      "performance_90_day": 0.0,
      "performance_annualized": 0.0,
      "total_stocks": 20
    },
    {
      "year": "2026",
      "month": "June",
      "day": "15",
      "file": "2026/June/15.tsv",
      "date": "2026-06-15",
      "performance_90_day": 0.0,
      "performance_annualized": 0.0,
      "total_stocks": 20
    }
  ]
}